{
    "test_run_parameters": {
        "language_tested": "french",
        "question_model": "llama3.1_8B-128k",
        "evaluator_model": "gemma2_9B-8k",
        "retrieval_algorithm": "zeroshot",
        "context_type": "token",
        "noise_level": 5000,
        "file_extension_tested": "txt"
    },
    "overall_metrics": {
        "accuracy": 0.5740740740740741,
        "precision": 0.5512820512820513,
        "recall": 0.7962962962962963,
        "specificity": 0.35185185185185186,
        "f1_score": 0.6515151515151515,
        "true_positives": 43,
        "true_negatives": 19,
        "false_positives": 35,
        "false_negatives": 11,
        "total_questions": 108,
        "dataset_self_evaluation_success": {
            "general_questions": 0.7962962962962963,
            "unanswerable_questions": 0.35185185185185186
        }
    },
    "timing": {
        "overall_duration_seconds": 0.0,
        "duration_qa_phase_seconds": 0.0,
        "duration_eval_phase_seconds": 0.0
    },
    "per_dataset_details": {
        "general_questions": {
            "results": [
                {
                    "question": "How many dosing openings are closed during fine application?",
                    "expected_answer": "Two of three dosing openings are closed.",
                    "model_answer": "2.",
                    "page": 24,
                    "dataset": "general_questions",
                    "self_evaluation": "yes"
                },
                {
                    "question": "What is the overlap percentage for the full field spreading pattern?",
                    "expected_answer": "100% overlap",
                    "model_answer": "100%",
                    "page": 28,
                    "dataset": "general_questions",
                    "self_evaluation": "yes"
                },
                {
                    "question": "What system continuously measures fertilizer quantity being spread?",
                    "expected_answer": "Weighcells continuously measure fertilizer quantity being spread.",
                    "model_answer": "The system of measurement is the \"capteurs de pesée\" (load cells) which measure the amount of fertilizer being spread.",
                    "page": 30,
                    "dataset": "general_questions",
                    "self_evaluation": "yes"
                },
                {
                    "question": "How often does the spreader carry out automatic calibration tests?",
                    "expected_answer": "Every 75 kg or every minute.",
                    "model_answer": "Every 75 kg or every minute.",
                    "page": 31,
                    "dataset": "general_questions",
                    "self_evaluation": "yes"
                },
                {
                    "question": "How can the tractor's driving speed be transmitted to the IsoMatch if the tractor lacks ISOBUS communication?",
                    "expected_answer": "By adding the IsoMatch power cable set to the tractor.",
                    "model_answer": "If the tractor is not equipped with ISOBUS communication, you can install the IsoMatch Power adapter. This allows to render the tractor fully compatible with ISOBUS and connect and control your machine via the IsoMatch Tellus terminal. The tractor's driving speed (or the trailed machine) is indicated on the IsoMatch Tellus via the ISOBUS technology.",
                    "page": 32,
                    "dataset": "general_questions",
                    "self_evaluation": "no"
                },
                {
                    "question": "Where is the main switch button to turn the control box on or off located?",
                    "expected_answer": "The main switch button is located on the upper left in the red extension.",
                    "model_answer": "The main switch button to turn the control box on or off is not explicitly mentioned in the provided text. However, according to the instructions for the IsoMatch Tellus GO (page 34), \"Le commutateur principal, en haut à gauche dans la bordure rouge, permet de connecter ou de déconnecter le boîtier de commande.\"",
                    "page": 34,
                    "dataset": "general_questions",
                    "self_evaluation": "yes"
                },
                {
                    "question": "How long should the main switch button be pressed to turn the control box on or off?",
                    "expected_answer": "At least 1 second.",
                    "model_answer": "1 seconde.",
                    "page": 34,
                    "dataset": "general_questions",
                    "self_evaluation": "yes"
                },
                {
                    "question": "After initial setup of the machine and after any maintenance or repairs, how long should the machine be operated before re-checking all nuts and bolts?",
                    "expected_answer": "1 hour",
                    "model_answer": "1 hour.",
                    "page": 38,
                    "dataset": "general_questions",
                    "self_evaluation": "yes"
                },
                {
                    "question": "How could the console assembly foot be mounted if no suitable mounting location exists in the cabin?",
                    "expected_answer": "A footplate could be made and welded to the pipe for the console foot.",
                    "model_answer": "Si vous n'avez pas d'emplacement de montage approprié dans la cabine, vous devez réaliser un socle pour insérer le tube servant de pied à la console.",
                    "page": 40,
                    "dataset": "general_questions",
                    "self_evaluation": "yes"
                },
                {
                    "question": "What torque (in NM) should be applied to the vane lock nuts?",
                    "expected_answer": "50NM",
                    "model_answer": "50NM.",
                    "page": 43,
                    "dataset": "general_questions",
                    "self_evaluation": "yes"
                },
                {
                    "question": "What determines the machine's working width?",
                    "expected_answer": "Spreading disc RPM",
                    "model_answer": "The machine's working width is determined by the speed of the spreader disc.",
                    "page": 46,
                    "dataset": "general_questions",
                    "self_evaluation": "no"
                },
                {
                    "question": "Where should the position sensor for the hydraulic border spreading plate be connected?",
                    "expected_answer": "In the electronic box on the spreader.",
                    "model_answer": "Raccordez le capteur de position au boîtier comportant l'électronique sur l'épandeur.",
                    "page": 47,
                    "dataset": "general_questions",
                    "self_evaluation": "yes"
                },
                {
                    "question": "What specific precaution should be taken before working between the tractor and machine to check the coupling shaft length?",
                    "expected_answer": "Place the machine on a supporting beam.",
                    "model_answer": "Contrôlez l'absence de pollution ou de dommages sur l'arbre de transmission et la pièce d'attelage.",
                    "page": 50,
                    "dataset": "general_questions",
                    "self_evaluation": "no"
                },
                {
                    "question": "Should the parking brake of the tractor be engaged before connecting the machine?",
                    "expected_answer": "Yes.",
                    "model_answer": "Yes.",
                    "page": 52,
                    "dataset": "general_questions",
                    "self_evaluation": "yes"
                },
                {
                    "question": "What is the maximum permissible operating angle in degrees for the coupling shaft, both when lifted and lowered?",
                    "expected_answer": "30 degrees",
                    "model_answer": "30°",
                    "page": 54,
                    "dataset": "general_questions",
                    "self_evaluation": "yes"
                },
                {
                    "question": "What must be ensured with decoupling ropes during power lift connection?",
                    "expected_answer": "Decoupling ropes must never be tense.",
                    "model_answer": "The cables must not be stretched and must have a sufficient freedom of movement.",
                    "page": 56,
                    "dataset": "general_questions",
                    "self_evaluation": "yes"
                },
                {
                    "question": "Below which application rate in kg/min is it advised to use the fine application?",
                    "expected_answer": "Below 40 kg/min.",
                    "model_answer": "<answer>\n40 kg/min\n</answer>",
                    "page": 66,
                    "dataset": "general_questions",
                    "self_evaluation": "yes"
                },
                {
                    "question": "What is the general formula for calculating the required flowrate of fertilizer in kg/min?",
                    "expected_answer": "Working width (m) x Driving speed (km/h) x Application rate (kg/ha) / 600",
                    "model_answer": "Vitesse d'écoulement requise (kg/min) = Largeur de travail (m) x vitesse d'avancement (km/h) / 600.",
                    "page": 68,
                    "dataset": "general_questions",
                    "self_evaluation": "no"
                },
                {
                    "question": "What type of serial connection does the IsoMatch control box use for communication?",
                    "expected_answer": "RS 232",
                    "model_answer": "RS232.",
                    "page": 72,
                    "dataset": "general_questions",
                    "self_evaluation": "yes"
                },
                {
                    "question": "When loading manually, what's the maximum distance in mm between the hopper rim and the ground before a platform is mandatory?",
                    "expected_answer": "1250 mm",
                    "model_answer": "1250 mm.",
                    "page": 74,
                    "dataset": "general_questions",
                    "self_evaluation": "yes"
                },
                {
                    "question": "What is the maximum distance in mm between spreader and loading platform?",
                    "expected_answer": "200 mm maximum distance between them.",
                    "model_answer": "200 mm.",
                    "page": 74,
                    "dataset": "general_questions",
                    "self_evaluation": "yes"
                },
                {
                    "question": "What does a tray test check on a fertilizer spreader?",
                    "expected_answer": "Fertilizer distribution pattern of the spreader.",
                    "model_answer": "A tray test checks the distribution of fertilizer and the fertilizer distributor.",
                    "page": 76,
                    "dataset": "general_questions",
                    "self_evaluation": "yes"
                },
                {
                    "question": "What materials are required to perform the tray test?",
                    "expected_answer": "A measuring tape or ruler, a spirit level, 7 troughs, 7 graduated tubes, a funnel, a notebook, pen, calculator, this manual, and the software's instruction manual.",
                    "model_answer": "A mètre à ruban ou règle graduée, un niveau à bulle, 7 bacs de collecte, 7 tubes de mesure, un entonnoir, des bloc-notes, un stylo et une calculatrice, ainsi que le manuel d'utilisation et le niveau des instructions du logiciel.",
                    "page": 77,
                    "dataset": "general_questions",
                    "self_evaluation": "yes"
                },
                {
                    "question": "What maximum wind speed in m/s is permissible for both the tray test and actual spreading?",
                    "expected_answer": "3 m/s)",
                    "model_answer": "3 m/s (force du vent 2)",
                    "page": 77,
                    "dataset": "general_questions",
                    "self_evaluation": "yes"
                },
                {
                    "question": "Before testing the ExactLine spreading pattern, what specific height in cm should the spreading disc be set to above the troughs?",
                    "expected_answer": "75 cm",
                    "model_answer": "75 cm.",
                    "page": 89,
                    "dataset": "general_questions",
                    "self_evaluation": "yes"
                },
                {
                    "question": "After disengaging the PTO shaft, what poses a continued danger and why?",
                    "expected_answer": "Inertia causes continued rotation.",
                    "model_answer": "The machine can pose a continued danger if you approach it while it is still in motion after disengaging the PTO shaft. This is because of the inertia of mass.",
                    "page": 94,
                    "dataset": "general_questions",
                    "self_evaluation": "yes"
                },
                {
                    "question": "According to the last setting check, what is the recommended height in centimeter of the spreader over the ground or crops?",
                    "expected_answer": "75 cm",
                    "model_answer": "75 cm.",
                    "page": 96,
                    "dataset": "general_questions",
                    "self_evaluation": "yes"
                },
                {
                    "question": "What happens when hopper content falls below 100 kg?",
                    "expected_answer": "Automatic calibration switches off.",
                    "model_answer": "Le système de commande coupe l'étalonnage automatique.",
                    "page": 101,
                    "dataset": "general_questions",
                    "self_evaluation": "yes"
                },
                {
                    "question": "What are the two functions for border spreading?",
                    "expected_answer": "Hydraulic border spreading plate and ExactLine.",
                    "model_answer": "Épandage unilatéral en bordure avec le déflecteur de bordure hydraulique et Épandage de bordure à l'aide du système ExactLine.",
                    "page": 106,
                    "dataset": "general_questions",
                    "self_evaluation": "yes"
                },
                {
                    "question": "What two actions must be done in the event of spreader failure or stoppage while using the spreader in the field?",
                    "expected_answer": " Stop spreading immediately and disconnect the PTO shaft immediately.",
                    "model_answer": "Arrêtez immédiatement d'épandre et débrayez immédiatement la prise de force.",
                    "page": 108,
                    "dataset": "general_questions",
                    "self_evaluation": "yes"
                },
                {
                    "question": "What should you do if a spreading disc spreads irregularly?",
                    "expected_answer": "Stop spreading and disconnect the PTO shaft immediately.",
                    "model_answer": "Débrayez immédiatement la prise de force.",
                    "page": 113,
                    "dataset": "general_questions",
                    "self_evaluation": "yes"
                },
                {
                    "question": "What is the maximum allowable temperature in degrees celsius when cleaning the machine with water or steam?",
                    "expected_answer": "40 degrees Celsius",
                    "model_answer": "40°C.",
                    "page": 117,
                    "dataset": "general_questions",
                    "self_evaluation": "yes"
                },
                {
                    "question": "What is the maximum allowable pressure in bar when cleaning the machine with water or steam?",
                    "expected_answer": "80 bar",
                    "model_answer": "80 bar.",
                    "page": 117,
                    "dataset": "general_questions",
                    "self_evaluation": "yes"
                },
                {
                    "question": "What specific precaution should be taken regarding white metal parts to prevent corrosion during winter storage?",
                    "expected_answer": "Preservative grease or preserving liquid.",
                    "model_answer": "Appliquer le liquide de protection fourni sur les parties métalliques (nues) de la machine pour les protéger de la corrosion.",
                    "page": 121,
                    "dataset": "general_questions",
                    "self_evaluation": "no"
                },
                {
                    "question": "What specific precaution should be taken before welding on the machine after using nitrate-containing fertilizer?",
                    "expected_answer": "Remove all fertilizer remnants.",
                    "model_answer": "Éloignez tous les résidus d'engrais des orifices, des angles, des manchons et des flexibles avant de souder, couper ou tailler sur la machine.",
                    "page": 123,
                    "dataset": "general_questions",
                    "self_evaluation": "yes"
                },
                {
                    "question": "How many grease nipples do the discharge bushings have?",
                    "expected_answer": "Two grease nipples per discharge bushing.",
                    "model_answer": "2",
                    "page": 126,
                    "dataset": "general_questions",
                    "self_evaluation": "yes"
                },
                {
                    "question": "What is the required grease level in mm below the filler opening for spreading disc gearboxes after the machine has stood still?",
                    "expected_answer": "35 mm",
                    "model_answer": "35 mm.",
                    "page": 127,
                    "dataset": "general_questions",
                    "self_evaluation": "yes"
                },
                {
                    "question": "What is the maximum hydraulic pressure allowed for the hydaulic system in bars?",
                    "expected_answer": "210 bars.",
                    "model_answer": "210 bars.",
                    "page": 131,
                    "dataset": "general_questions",
                    "self_evaluation": "yes"
                },
                {
                    "question": "What is the required distance in mm between the rope and discharge bushing opening?",
                    "expected_answer": "109 mm.",
                    "model_answer": "109 mm.",
                    "page": 136,
                    "dataset": "general_questions",
                    "self_evaluation": "yes"
                },
                {
                    "question": "How often should the agitator axle seal be replaced?",
                    "expected_answer": "Every season and after every 100 operational hours.",
                    "model_answer": "The agitator axle seal should be replaced every 100 hours of machine use.",
                    "page": 140,
                    "dataset": "general_questions",
                    "self_evaluation": "yes"
                },
                {
                    "question": "From which version does the ISOBUS support the reception of the signal of the Greenseeker sensor?",
                    "expected_answer": "06.00.00.0257",
                    "model_answer": "A partir de la version 06.00.00.0257 du GreenSeeker.",
                    "page": 27,
                    "dataset": "general_questions",
                    "self_evaluation": "yes"
                },
                {
                    "question": "When shortening a coupling shaft, how far must profiled tubes at least overlap in mm?",
                    "expected_answer": "150mm.",
                    "model_answer": "25 mm.",
                    "page": 51,
                    "dataset": "general_questions",
                    "self_evaluation": "no"
                },
                {
                    "question": "How many parts does the distribution meter have?",
                    "expected_answer": "Seven.",
                    "model_answer": "The granulomètre (distribution meter) has 4 small compartments separated by 7 other compartments.",
                    "page": 59,
                    "dataset": "general_questions",
                    "self_evaluation": "no"
                },
                {
                    "question": "How to enable fine application for dosing low application rate?",
                    "expected_answer": "Move the fine application handle to the fine dosing position on both sides.",
                    "model_answer": "Use the kit of dosage fin (fine) when the desired flow rate is less than 40 kg/min.",
                    "page": 67,
                    "dataset": "general_questions",
                    "self_evaluation": "no"
                },
                {
                    "question": "What is the symbol on top of the fine application handle indicating that the Fine application kit is enabled?",
                    "expected_answer": "1 open hole and 2 thick holes",
                    "model_answer": "1 rond ouvert (orifice de dosage)",
                    "page": 67,
                    "dataset": "general_questions",
                    "self_evaluation": "no"
                },
                {
                    "question": "Where is the RS 232 connector located?",
                    "expected_answer": "At the back of the control box.",
                    "model_answer": "The RS 232 connector is located on the back of the control box.",
                    "page": 72,
                    "dataset": "general_questions",
                    "self_evaluation": "yes"
                },
                {
                    "question": "How often should the left and right spreading disc be checked if they spread the same volumes of fertiliser to ensure good distribution?",
                    "expected_answer": "Every year",
                    "model_answer": "Once a year.",
                    "page": 78,
                    "dataset": "general_questions",
                    "self_evaluation": "yes"
                },
                {
                    "question": "What is the maximum fertilizer loss of the quantity in the middle trough in percent allowed in a ditch?",
                    "expected_answer": "10% of the quantity in the middle trough",
                    "model_answer": "10%",
                    "page": 91,
                    "dataset": "general_questions",
                    "self_evaluation": "yes"
                },
                {
                    "question": "From which machine point is the spreading height measured to the ground or the crop?",
                    "expected_answer": "Measured from the bottom of the vanes.",
                    "model_answer": "The spreading height is measured from the lower part of the vanes.",
                    "page": 95,
                    "dataset": "general_questions",
                    "self_evaluation": "yes"
                },
                {
                    "question": "What information is available so that I  can set the correct PTO shaft and spreading disc RPM?",
                    "expected_answer": "spreading chart or online spreading chart",
                    "model_answer": "The information needed to set the correct PTO shaft and spreading disc RPM is found in the table of operation for the ExactLine system on page 110.",
                    "page": 111,
                    "dataset": "general_questions",
                    "self_evaluation": "no"
                },
                {
                    "question": "What should I do if I cannot lower the power lift far enough to release the catch hooks when preparing the machine for storage?",
                    "expected_answer": "Place the spreader on a firm, stable ramp",
                    "model_answer": "Si vous ne pouvez pas faire descendre le levage de puissance suffisamment bas pour libérer les crochet de retenue lors de la préparation de la machine pour le stockage, placez l'épandeur sur un élément en hauteur stable et solide, par exemple une palette.",
                    "page": 120,
                    "dataset": "general_questions",
                    "self_evaluation": "no"
                },
                {
                    "question": "What type of grease is the central gearbox filled with?",
                    "expected_answer": "EP 00/000 gear grease.",
                    "model_answer": "EP 00/000.",
                    "page": 127,
                    "dataset": "general_questions",
                    "self_evaluation": "yes"
                },
                {
                    "question": "What is the required distance in mm between the discharge bushing and spreading disc?",
                    "expected_answer": "The required distance is 1.0 mm.",
                    "model_answer": "1.0 mm",
                    "page": 138,
                    "dataset": "general_questions",
                    "self_evaluation": "yes"
                },
                {
                    "question": "Can you connect the tractor's speed sensor  or radar to the IsoMatch control box?",
                    "expected_answer": "Yes, using the Sensor input IM Tellus.",
                    "model_answer": "Oui, vous pouvez raccorder le capteur de vitesse du tracteur ou le radar au boîtier de commande IsoMatch Tellus.",
                    "page": 144,
                    "dataset": "general_questions",
                    "self_evaluation": "yes"
                }
            ]
        },
        "table_questions": {
            "results": [
                {
                    "question": "What is the pattern of the type 'mineral'?",
                    "expected_answer": "angular, with sharp angles and edges",
                    "model_answer": "Type 2.",
                    "page": 58,
                    "dataset": "table_questions",
                    "self_evaluation": "no"
                },
                {
                    "question": "What is the hopper weight without hopper cover in kg of the Exacta-TLX GEOSPREAD 3225?",
                    "expected_answer": "337.5 kg",
                    "model_answer": "2550.",
                    "page": 36,
                    "dataset": "table_questions",
                    "self_evaluation": "no"
                },
                {
                    "question": "What is the weight in kg of the Exacta-TLX GEOSPREAD 3900?",
                    "expected_answer": "795 kg",
                    "model_answer": "10\n</answer>",
                    "page": 36,
                    "dataset": "table_questions",
                    "self_evaluation": "no"
                },
                {
                    "question": "What is the sound level in dB of a Tractor + spreading spreader (Kali 60) with its rear window opened?",
                    "expected_answer": "84.6 dB",
                    "model_answer": "76.2",
                    "page": 37,
                    "dataset": "table_questions",
                    "self_evaluation": "no"
                },
                {
                    "question": "How often (in what interval) must the condition of the vanes be inspected?",
                    "expected_answer": "daily",
                    "model_answer": "Every 10 hours.",
                    "page": 125,
                    "dataset": "table_questions",
                    "self_evaluation": "no"
                },
                {
                    "question": "How often (in what interval) must the bushing height be checked and the discharge be set?",
                    "expected_answer": "after the first 10 hours and every 100 hours, but a minimum of once per year",
                    "model_answer": "Every 10 hours.",
                    "page": 125,
                    "dataset": "table_questions",
                    "self_evaluation": "no"
                },
                {
                    "question": "How often (in what interval) must the agitator seal be replaced?",
                    "expected_answer": "every 100 hours or if worn",
                    "model_answer": "Every 10 hours.",
                    "page": 125,
                    "dataset": "table_questions",
                    "self_evaluation": "no"
                },
                {
                    "question": "With what torque in Nm must a M18 hexagon steel bolt with a 10.9 quality and with a 0.13 friction be fastened?",
                    "expected_answer": "420 Nm",
                    "model_answer": "70",
                    "page": 129,
                    "dataset": "table_questions",
                    "self_evaluation": "no"
                },
                {
                    "question": "With what torque in Nm must a M6 hexagon stainless steel bolt with a 70 (A2) quality and with a 0.2 friction be fastened?",
                    "expected_answer": "9.9 Nm",
                    "model_answer": "10.9",
                    "page": 129,
                    "dataset": "table_questions",
                    "self_evaluation": "no"
                },
                {
                    "question": "What should I do if the flow of the fertiliser is blocked, at what page should I look?",
                    "expected_answer": "Clean the machine well after each use. Replace the agitator if it is worn out. The page is 118",
                    "model_answer": "Page 118.",
                    "page": 152,
                    "dataset": "table_questions",
                    "self_evaluation": "yes"
                }
            ]
        },
        "unanswerable_questions": {
            "results": [
                {
                    "question": "How much extra diesel does the tractor consume to use the Exacta-TLX GEOSPREAD?",
                    "expected_answer": "Not found in context",
                    "model_answer": "Unknown",
                    "page": 23,
                    "dataset": "unanswerable_questions",
                    "self_evaluation": "yes"
                },
                {
                    "question": "Is fine application more expensive than normal dosing?",
                    "expected_answer": "Not found in context",
                    "model_answer": "Non.",
                    "page": 24,
                    "dataset": "unanswerable_questions",
                    "self_evaluation": "no"
                },
                {
                    "question": "Is one-sided boundary spreading suitable for small gardens?",
                    "expected_answer": "Not found in context",
                    "model_answer": "Yes.",
                    "page": 28,
                    "dataset": "unanswerable_questions",
                    "self_evaluation": "no"
                },
                {
                    "question": "For what other kind of connections can the IM Tellus Input cable be used?",
                    "expected_answer": "Not found in context",
                    "model_answer": "The IsoMatch Tellus Input cable is compatible with a tractor equipped with an ISOBUS system.",
                    "page": 32,
                    "dataset": "unanswerable_questions",
                    "self_evaluation": "no"
                },
                {
                    "question": "Can the IsoMatch universal ISOBUS terminal be used to check the weather?",
                    "expected_answer": "Not found in context",
                    "model_answer": "No. The text does not mention anything about using the IsoMatch universal ISOBUS terminal to check the weather.",
                    "page": 33,
                    "dataset": "unanswerable_questions",
                    "self_evaluation": "yes"
                },
                {
                    "question": "Can IsoMatch Tellus be connected to an external mouse?",
                    "expected_answer": "Not found in context",
                    "model_answer": "Yes.",
                    "page": 34,
                    "dataset": "unanswerable_questions",
                    "self_evaluation": "no"
                },
                {
                    "question": "Is the Hydraulic border spreading plate made out of steel?",
                    "expected_answer": "Not found in context",
                    "model_answer": "No.",
                    "page": 47,
                    "dataset": "unanswerable_questions",
                    "self_evaluation": "no"
                },
                {
                    "question": "Can the linkage pin for the tractor be made out of aluminium?",
                    "expected_answer": "Not found in context",
                    "model_answer": "Unknown. The text does not mention anything about the material the linkage pin is made of.",
                    "page": 53,
                    "dataset": "unanswerable_questions",
                    "self_evaluation": "yes"
                },
                {
                    "question": "Can the tray test be performed at 40 degrees Celsius?",
                    "expected_answer": "Not found in context",
                    "model_answer": "Non.",
                    "page": 77,
                    "dataset": "unanswerable_questions",
                    "self_evaluation": "no"
                },
                {
                    "question": "Can the hydraulic border spreading plate be actuated pneumatically?",
                    "expected_answer": "Not found in context",
                    "model_answer": "No. The text does not mention anything about a \"hydraulic border spreading plate\" being able to be actuated pneumatically.",
                    "page": 85,
                    "dataset": "unanswerable_questions",
                    "self_evaluation": "no"
                },
                {
                    "question": "By which environmental standards is the maximum acceptable loss in the ditch is determined?",
                    "expected_answer": "Not found in context",
                    "model_answer": "A norme environnementale.",
                    "page": 87,
                    "dataset": "unanswerable_questions",
                    "self_evaluation": "no"
                },
                {
                    "question": "How should one proceed to stop spreading the fertilizer?",
                    "expected_answer": "Not found in context",
                    "model_answer": "Fermez les unités de dosage en appuyant sur la touche \"STOP\" pour effectuer le demi-tour sur tournière.",
                    "page": 100,
                    "dataset": "unanswerable_questions",
                    "self_evaluation": "no"
                },
                {
                    "question": "What is the maximum height the fertilizer flies when spreading without GEOCONTROL headland",
                    "expected_answer": "Not found in context",
                    "model_answer": "10% of the amount spread behind the spreader = 100%.",
                    "page": 103,
                    "dataset": "unanswerable_questions",
                    "self_evaluation": "no"
                },
                {
                    "question": "What is seven-sided boundary spreading with the hydraulicborder spreading plate?",
                    "expected_answer": "Not found in context",
                    "model_answer": "Épandage unilatéral en bordure avec le déflecteur de bordure hydraulique.",
                    "page": 107,
                    "dataset": "unanswerable_questions",
                    "self_evaluation": "no"
                },
                {
                    "question": "Which appropriate measures for road transport should be taken when stopping work?",
                    "expected_answer": "Not found in context",
                    "model_answer": "Coupez le moteur du tracteur, retirez la clé du contact et serrez le frein à main sur le tracteur.",
                    "page": 112,
                    "dataset": "unanswerable_questions",
                    "self_evaluation": "no"
                },
                {
                    "question": "Why do most types of fertiliser attract water?",
                    "expected_answer": "Not found in context",
                    "model_answer": "Most types of fertilisers absorb water.",
                    "page": 114,
                    "dataset": "unanswerable_questions",
                    "self_evaluation": "yes"
                },
                {
                    "question": "Why is damage to the vanes, spreading disc or discharge bushing, most likely caused by a hard object?",
                    "expected_answer": "Not found in context",
                    "model_answer": "A hard object.",
                    "page": 115,
                    "dataset": "unanswerable_questions",
                    "self_evaluation": "no"
                },
                {
                    "question": "What should a person do who fell into the fertilizer and no physician is available?",
                    "expected_answer": "Not found in context",
                    "model_answer": "Consultez le cas échéant un médecin.",
                    "page": 117,
                    "dataset": "unanswerable_questions",
                    "self_evaluation": "no"
                },
                {
                    "question": "What happens if the machine grease nipples are never lubricated?",
                    "expected_answer": "Not found in context",
                    "model_answer": "If the machine grease nipples are not lubricated, they can lead to corrosion.",
                    "page": 118,
                    "dataset": "unanswerable_questions",
                    "self_evaluation": "no"
                },
                {
                    "question": "What specific paint should be used to paint any damaged paintwork at the end of the season the machine in preparation for winter storage?",
                    "expected_answer": "Not found in context",
                    "model_answer": "Shell Rodina 2 or Castrol GS2.",
                    "page": 121,
                    "dataset": "unanswerable_questions",
                    "self_evaluation": "no"
                },
                {
                    "question": "What is the curriculum of the training program agrarians need to complete to be considered competent to operate this machine?",
                    "expected_answer": "Not found in context",
                    "model_answer": "A person is qualified if they have completed the training required by national authorities.",
                    "page": 4,
                    "dataset": "unanswerable_questions",
                    "self_evaluation": "no"
                },
                {
                    "question": "By which international standard are the pictograms used in this manual specified for agricultural machinery?",
                    "expected_answer": "Not found in context",
                    "model_answer": "The manual does not specify a particular international standard for the pictograms used. However, it mentions that the pictograms are intended to help find certain parts of the text easily.",
                    "page": 5,
                    "dataset": "unanswerable_questions",
                    "self_evaluation": "no"
                },
                {
                    "question": "How does the rate of corrosion on the Exacta-TLX GEOSPREAD compare between machines used in coastal vs. inland agricultural regions?",
                    "expected_answer": "Not found in context",
                    "model_answer": "Unknown",
                    "page": 21,
                    "dataset": "unanswerable_questions",
                    "self_evaluation": "yes"
                },
                {
                    "question": "What kind of protective safety gloves are needed for cleaning fertiliser remnants from the Exacta-TLX GEOSPREAD before welding?",
                    "expected_answer": "Not found in context",
                    "model_answer": "Gants protecteurs.",
                    "page": 22,
                    "dataset": "unanswerable_questions",
                    "self_evaluation": "no"
                },
                {
                    "question": "What are the detailed technical specifications and bandwidth capabilities of different ISOBUS communication protocol versions compatible with the IsoMatch Tellus system?",
                    "expected_answer": "Not found in context",
                    "model_answer": "The text does not provide a clear answer to the question about the technical specifications of different ISOBUS communication protocol versions. However, I can infer some information from the provided context.\n\nAccording to page 32, the IsoMatch system is compatible with the following tracteurs:\n\n* Tracteur ISOBUS\n* Tracteur avec IsoMatch\n\nThe text does not provide specific details about the technical specifications of different ISOBUS communication protocol versions. However, it mentions that the Exacta-TLX-GEOSPREAD has the following characteristics (page 36):\n\n* Capacité (l): 1875, 2550, 3225, or 3900\n* Largeur de travail (m): 24, 27/28, 30, 32/33, 36, 39, 42\n\nIt is not clear which of these specifications are related to the ISOBUS communication protocol versions.",
                    "page": 32,
                    "dataset": "unanswerable_questions",
                    "self_evaluation": "yes"
                },
                {
                    "question": "How many hours of continuous operation can the IsoMatch Tellus operate before flattening a typical tractor battery if left switched on with the engine off?",
                    "expected_answer": "Not found in context",
                    "model_answer": "Unknown",
                    "page": 34,
                    "dataset": "unanswerable_questions",
                    "self_evaluation": "yes"
                },
                {
                    "question": "What specific 'grease' type is recommended for 'profiled tubes' of the  coupling shaft?",
                    "expected_answer": "Not found in context",
                    "model_answer": "The text does not explicitly state a specific type of grease. However, it mentions \"graissage\" (greasing) in several places, but it is referring to the process of applying lubricant to the transmission components, rather than specifying a particular type of grease.\n\nHowever, based on general knowledge and common practices for equipment maintenance, it can be inferred that a suitable grease for the profiled tubes would typically be a high-quality hydraulic grease with good mechanical properties.",
                    "page": 51,
                    "dataset": "unanswerable_questions",
                    "self_evaluation": "no"
                },
                {
                    "question": "What is the 'hose coupling support' made of?",
                    "expected_answer": "Not found in context",
                    "model_answer": "Unknown",
                    "page": 55,
                    "dataset": "unanswerable_questions",
                    "self_evaluation": "yes"
                },
                {
                    "question": "What specific type of 'Delicia Schnecken Linsen' slug pellets were used for the spreading chart example?",
                    "expected_answer": "Not found in context",
                    "model_answer": "Unknown",
                    "page": 69,
                    "dataset": "unanswerable_questions",
                    "self_evaluation": "yes"
                },
                {
                    "question": "What is the minimum 'baud rate' for 'RS 232 connection'?",
                    "expected_answer": "Not found in context",
                    "model_answer": "Unknown",
                    "page": 72,
                    "dataset": "unanswerable_questions",
                    "self_evaluation": "yes"
                },
                {
                    "question": "What is the maximum acceptable 'chunk' size of fertilizer in mm to prevent blockage?",
                    "expected_answer": "Not found in context",
                    "model_answer": "1250 mm.",
                    "page": 74,
                    "dataset": "unanswerable_questions",
                    "self_evaluation": "no"
                },
                {
                    "question": "What is the 'tap' material used for hydraulic border spreading plate tap?",
                    "expected_answer": "Not found in context",
                    "model_answer": "Unknown",
                    "page": 85,
                    "dataset": "unanswerable_questions",
                    "self_evaluation": "yes"
                },
                {
                    "question": "What type of 'active carbon filters' are recommended for closed tractor cabin to filter fertilizer dust?",
                    "expected_answer": "Not found in context",
                    "model_answer": "Active carbon filters.",
                    "page": 94,
                    "dataset": "unanswerable_questions",
                    "self_evaluation": "no"
                },
                {
                    "question": "What is the tolerance for 'measured distance from the bottom of the vanes, the distance to the ground or the crop' in cm?",
                    "expected_answer": "Not found in context",
                    "model_answer": "75 cm.",
                    "page": 95,
                    "dataset": "unanswerable_questions",
                    "self_evaluation": "no"
                },
                {
                    "question": "What is the typical 'wind speed' limit in m/sec before spreading quality becomes unacceptable?",
                    "expected_answer": "Not found in context",
                    "model_answer": "Unknown",
                    "page": 96,
                    "dataset": "unanswerable_questions",
                    "self_evaluation": "yes"
                },
                {
                    "question": "What is the recommended tire pressure 'range' for transport mode?",
                    "expected_answer": "Not found in context",
                    "model_answer": "Unknown",
                    "page": 93,
                    "dataset": "unanswerable_questions",
                    "self_evaluation": "yes"
                },
                {
                    "question": "What is the optimal driving speed reduction percentage during border spreading to compensate for application rate?",
                    "expected_answer": "Not found in context",
                    "model_answer": "75%",
                    "page": 106,
                    "dataset": "unanswerable_questions",
                    "self_evaluation": "no"
                },
                {
                    "question": "What is the distance tolerance in meters from field edge when driving 'first path' for border spreading?",
                    "expected_answer": "Not found in context",
                    "model_answer": "2 mètres.",
                    "page": 109,
                    "dataset": "unanswerable_questions",
                    "self_evaluation": "no"
                },
                {
                    "question": "Can the parking support withstand storage on a slope of 10 degrees?",
                    "expected_answer": "Not found in context",
                    "model_answer": "Unknown. The text does not provide specific information about the parking support's ability to withstand a storage on a slope of 10 degrees.",
                    "page": 119,
                    "dataset": "unanswerable_questions",
                    "self_evaluation": "yes"
                },
                {
                    "question": "What should be done at the start of the spring season, specifically to 'prepare it for the work', beyond cleaning and lubrication?",
                    "expected_answer": "Not found in context",
                    "model_answer": "Before storing the machine for a period of time, it is recommended to grease, clean, then grease again.",
                    "page": 121,
                    "dataset": "unanswerable_questions",
                    "self_evaluation": "no"
                },
                {
                    "question": "How many operational hours can 'vanes' typically last before requiring replacement?",
                    "expected_answer": "Not found in context",
                    "model_answer": "Unknown",
                    "page": 125,
                    "dataset": "unanswerable_questions",
                    "self_evaluation": "yes"
                },
                {
                    "question": "What type of 'universal grease' is recommended for all 'lubricating nipples'?",
                    "expected_answer": "Not found in context",
                    "model_answer": "Shell Rodina 2, Castrol GS2 or equivalent.",
                    "page": 126,
                    "dataset": "unanswerable_questions",
                    "self_evaluation": "no"
                },
                {
                    "question": "What type of 'suitable lubricant' is recommended for 'connectors' to prevent corrosion?",
                    "expected_answer": "Not found in context",
                    "model_answer": "EP00/000.",
                    "page": 128,
                    "dataset": "unanswerable_questions",
                    "self_evaluation": "no"
                },
                {
                    "question": "What 'screwdriver' type (flathead/phillips) is optimal for adjusting 'dosing mechanism'?",
                    "expected_answer": "Not found in context",
                    "model_answer": "The text does not explicitly state a specific screwdriver type (flathead or Phillips) is optimal for adjusting the \"dosing mechanism\". However, based on the context, it can be inferred that a flathead screwdriver is used to adjust the dosing mechanism.",
                    "page": 133,
                    "dataset": "unanswerable_questions",
                    "self_evaluation": "no"
                },
                {
                    "question": "What is the typical agitator 'seal ring' lifespan in operational hours before requiring replacement?",
                    "expected_answer": "Not found in context",
                    "model_answer": "6 ans maximum.",
                    "page": 134,
                    "dataset": "unanswerable_questions",
                    "self_evaluation": "no"
                },
                {
                    "question": "What is the 'small crack of light' dimension in millimeters between 'dosing baffles' when closed?",
                    "expected_answer": "Not found in context",
                    "model_answer": "109 mm.",
                    "page": 135,
                    "dataset": "unanswerable_questions",
                    "self_evaluation": "no"
                },
                {
                    "question": "What type of 'feeler gauge' material is recommended for 'discharge bushing height' check?",
                    "expected_answer": "Not found in context",
                    "model_answer": "Plastique.",
                    "page": 138,
                    "dataset": "unanswerable_questions",
                    "self_evaluation": "no"
                },
                {
                    "question": "What is the 'plastic seal' material specification for agitator axle seal?",
                    "expected_answer": "Not found in context",
                    "model_answer": "The plastic seal material for the agitateur (agitator) is not explicitly mentioned in the provided text. However, it is stated that the seal should be replaced at the beginning of each season and after every 100 hours of machine use.",
                    "page": 140,
                    "dataset": "unanswerable_questions",
                    "self_evaluation": "yes"
                },
                {
                    "question": "What is the material of the 'metal seal rings' for agitator axle seal?",
                    "expected_answer": "Not found in context",
                    "model_answer": "Plastique.",
                    "page": 141,
                    "dataset": "unanswerable_questions",
                    "self_evaluation": "no"
                },
                {
                    "question": "What specific 'extension cable' length in meters is optimal for ISO 11786 in cab tractor connection?",
                    "expected_answer": "Not found in context",
                    "model_answer": "Not found in context.",
                    "page": 144,
                    "dataset": "unanswerable_questions",
                    "self_evaluation": "yes"
                },
                {
                    "question": "What is the free 'test period' duration in days for 'GEOCONTROL software' user licence?",
                    "expected_answer": "Not found in context",
                    "model_answer": "Unknown",
                    "page": 145,
                    "dataset": "unanswerable_questions",
                    "self_evaluation": "yes"
                },
                {
                    "question": "What valve type and manufacturer is used for 'valve set' that comes with hopper empty sensor?",
                    "expected_answer": "Not found in context",
                    "model_answer": "The text does not explicitly state the specific valve type and manufacturer used for the 'valve set' that comes with the hopper empty sensor. However, based on the context, we can infer that the valve is part of the \"IsoMatch Tellus\" system, which is a precision application forage equipment.",
                    "page": 148,
                    "dataset": "unanswerable_questions",
                    "self_evaluation": "no"
                },
                {
                    "question": "What is the drain rate in liters per minute of 'drain kit' for hopper emptying?",
                    "expected_answer": "Not found in context",
                    "model_answer": "Not found in context.",
                    "page": 149,
                    "dataset": "unanswerable_questions",
                    "self_evaluation": "yes"
                },
                {
                    "question": "What 'sail' material is used for hopper cover, and its UV resistance?",
                    "expected_answer": "Not found in context",
                    "model_answer": "The text does not explicitly state what type of material is used for the hopper cover. However, it mentions \"La jupe\" (bâche) in page 150 which is translated to \"Bâche\" or \"Hopper cover\". It also mentions that the bâche can be made of a material that protects the fertilizer from humidity and pollution.\n\nThe text does not provide information on the UV resistance of the hopper cover.",
                    "page": 150,
                    "dataset": "unanswerable_questions",
                    "self_evaluation": "no"
                }
            ]
        }
    }
}