[
    {
        "question": "How many dosing openings are closed during fine application?",
        "expected_answer": "Two of three dosing openings are closed.",
        "model_answer": "The answer is not explicitly stated in the text. However, based on the context, we can infer that there are 2 dosing openings closed during fine application.\n\nThe text mentions \"Im Feindosierstand sind 2 der 3 Dosier\u00f6ffnungen geschlossen.\" which means that 2 out of 3 dosing openings are closed in the \"Feindosieren\" position.",
        "target_page": 24,
        "context_type": "token",
        "noise_level": 30000,
        "model_name": "llama3.1_8B-128k",
        "self_evaluation": "yes",
        "dataset": "question_datasets/question_answers_pairs.json",
        "file_extension": "xml",
        "duration": 16.9
    },
    {
        "question": "What is the overlap percentage for the full field spreading pattern?",
        "expected_answer": "100% overlap",
        "model_answer": "The overlap percentage for the full field spreading pattern is 100%.",
        "target_page": 28,
        "context_type": "token",
        "noise_level": 30000,
        "model_name": "llama3.1_8B-128k",
        "self_evaluation": "yes",
        "dataset": "question_datasets/question_answers_pairs.json",
        "file_extension": "xml",
        "duration": 15.9
    },
    {
        "question": "What system continuously measures fertilizer quantity being spread?",
        "expected_answer": "Weighcells continuously measure fertilizer quantity being spread.",
        "model_answer": "The system that continuously measures fertilizer quantity is called ExactLine.",
        "target_page": 30,
        "context_type": "token",
        "noise_level": 30000,
        "model_name": "llama3.1_8B-128k",
        "self_evaluation": "no",
        "dataset": "question_datasets/question_answers_pairs.json",
        "file_extension": "xml",
        "duration": 15.9
    },
    {
        "question": "How often does the spreader carry out automatic calibration tests?",
        "expected_answer": "Every 75 kg or every minute.",
        "model_answer": "The spreader carries out automatic calibration tests every 75 kg or every minute.",
        "target_page": 31,
        "context_type": "token",
        "noise_level": 30000,
        "model_name": "llama3.1_8B-128k",
        "self_evaluation": "yes",
        "dataset": "question_datasets/question_answers_pairs.json",
        "file_extension": "xml",
        "duration": 15.9
    },
    {
        "question": "How can the tractor's driving speed be transmitted to the IsoMatch if the tractor lacks ISOBUS communication?",
        "expected_answer": "By adding the IsoMatch power cable set to the tractor.",
        "model_answer": "The tractor's driving speed can be transmitted to the IsoMatch by using a GPS signal.",
        "target_page": 32,
        "context_type": "token",
        "noise_level": 30000,
        "model_name": "llama3.1_8B-128k",
        "self_evaluation": "no",
        "dataset": "question_datasets/question_answers_pairs.json",
        "file_extension": "xml",
        "duration": 16.0
    },
    {
        "question": "Where is the main switch button to turn the control box on or off located?",
        "expected_answer": "The main switch button is located on the upper left in the red extension.",
        "model_answer": "The main switch button to turn the control box on or off is located at the bottom right of the control box.",
        "target_page": 34,
        "context_type": "token",
        "noise_level": 30000,
        "model_name": "llama3.1_8B-128k",
        "self_evaluation": "no",
        "dataset": "question_datasets/question_answers_pairs.json",
        "file_extension": "xml",
        "duration": 16.1
    },
    {
        "question": "How long should the main switch button be pressed to turn the control box on or off?",
        "expected_answer": "At least 1 second.",
        "model_answer": "The main switch button should be pressed for 1 second.",
        "target_page": 34,
        "context_type": "token",
        "noise_level": 30000,
        "model_name": "llama3.1_8B-128k",
        "self_evaluation": "yes",
        "dataset": "question_datasets/question_answers_pairs.json",
        "file_extension": "xml",
        "duration": 0.4
    },
    {
        "question": "After initial setup of the machine and after any maintenance or repairs, how long should the machine be operated before re-checking all nuts and bolts?",
        "expected_answer": "1 hour",
        "model_answer": "The machine should not be operated for at least 1 hour after initial setup or any maintenance or repairs.",
        "target_page": 38,
        "context_type": "token",
        "noise_level": 30000,
        "model_name": "llama3.1_8B-128k",
        "self_evaluation": "yes",
        "dataset": "question_datasets/question_answers_pairs.json",
        "file_extension": "xml",
        "duration": 16.0
    },
    {
        "question": "How could the console assembly foot be mounted if no suitable mounting location exists in the cabin?",
        "expected_answer": "A footplate could be made and welded to the pipe for the console foot.",
        "model_answer": "The text does not provide a direct answer to the question. However, I can infer an answer based on the context.\n\nIf there is no suitable mounting location in the cabin for the console assembly foot, you should install a footplate before installing the console. The footplate should be installed on a solid ground and then the console can be mounted on it.",
        "target_page": 40,
        "context_type": "token",
        "noise_level": 30000,
        "model_name": "llama3.1_8B-128k",
        "self_evaluation": "no",
        "dataset": "question_datasets/question_answers_pairs.json",
        "file_extension": "xml",
        "duration": 16.8
    },
    {
        "question": "What torque (in NM) should be applied to the vane lock nuts?",
        "expected_answer": "50NM",
        "model_answer": "The answer is: 50 Nm.",
        "target_page": 43,
        "context_type": "token",
        "noise_level": 30000,
        "model_name": "llama3.1_8B-128k",
        "self_evaluation": "yes",
        "dataset": "question_datasets/question_answers_pairs.json",
        "file_extension": "xml",
        "duration": 15.8
    },
    {
        "question": "What determines the machine's working width?",
        "expected_answer": "Spreading disc RPM",
        "model_answer": "The machine's working width is determined by the position of the Gelenkwelle (Gelenkwellenl\u00e4nge) in relation to the Antriebswelle (Zapfwellendrehzahl).",
        "target_page": 46,
        "context_type": "token",
        "noise_level": 30000,
        "model_name": "llama3.1_8B-128k",
        "self_evaluation": "no",
        "dataset": "question_datasets/question_answers_pairs.json",
        "file_extension": "xml",
        "duration": 16.3
    },
    {
        "question": "Where should the position sensor for the hydraulic border spreading plate be connected?",
        "expected_answer": "In the electronic box on the spreader.",
        "model_answer": "The position sensor for the hydraulic border spreading plate should be connected to the machine's electronic control unit.",
        "target_page": 47,
        "context_type": "token",
        "noise_level": 30000,
        "model_name": "llama3.1_8B-128k",
        "self_evaluation": "yes",
        "dataset": "question_datasets/question_answers_pairs.json",
        "file_extension": "xml",
        "duration": 16.0
    },
    {
        "question": "What specific precaution should be taken before working between the tractor and machine to check the coupling shaft length?",
        "expected_answer": "Place the machine on a supporting beam.",
        "model_answer": "The correct answer is: \"Check the coupling shaft length by measuring the distance between the PTO (Power take-off) shaft of the tractor and the drive shaft of the machine.\"",
        "target_page": 50,
        "context_type": "token",
        "noise_level": 30000,
        "model_name": "llama3.1_8B-128k",
        "self_evaluation": "no",
        "dataset": "question_datasets/question_answers_pairs.json",
        "file_extension": "xml",
        "duration": 16.3
    },
    {
        "question": "What is the maximum operating angle of the coupling shaft when lifted and when lowered?",
        "expected_answer": "The maximum operating angle of the coupling shaft is 30\u00b0 when lifted and 30\u00b0 when lowered.",
        "model_answer": "The maximum operating angle of the coupling shaft is 30\u00b0 above and 30\u00b0 below.",
        "target_page": 51,
        "context_type": "token",
        "noise_level": 30000,
        "model_name": "llama3.1_8B-128k",
        "self_evaluation": "yes",
        "dataset": "question_datasets/question_answers_pairs.json",
        "file_extension": "xml",
        "duration": 16.0
    },
    {
        "question": "Should the parking brake of the tractor be engaged before connecting the machine?",
        "expected_answer": "Yes.",
        "model_answer": "The answer is: Yes. The parking brake of the tractor should be engaged before connecting the machine.",
        "target_page": 52,
        "context_type": "token",
        "noise_level": 30000,
        "model_name": "llama3.1_8B-128k",
        "self_evaluation": "yes",
        "dataset": "question_datasets/question_answers_pairs.json",
        "file_extension": "xml",
        "duration": 16.0
    },
    {
        "question": "What is the maximum permissible operating angle in degrees for the coupling shaft, both when lifted and lowered?",
        "expected_answer": "30 degrees",
        "model_answer": "The maximum permissible operating angle of the coupling shaft is 30\u00b0.",
        "target_page": 54,
        "context_type": "token",
        "noise_level": 30000,
        "model_name": "llama3.1_8B-128k",
        "self_evaluation": "yes",
        "dataset": "question_datasets/question_answers_pairs.json",
        "file_extension": "xml",
        "duration": 15.9
    },
    {
        "question": "What must be ensured with decoupling ropes during power lift connection?",
        "expected_answer": "Decoupling ropes must never be tense.",
        "model_answer": "The text does not explicitly state what should be ensured when using decoupling ropes during power lift connection. However, based on the context, it can be inferred that the correct answer is:\n\n* The Gelenkwelle (Gelenkwellenl\u00e4nge) must be checked and adjusted to ensure proper length.\n* The safety chains of the Schutzrohre (Schutzrohren) must be installed at both ends of the Gelenkwelle.\n\nThis information can be found in the text on page 51.",
        "target_page": 56,
        "context_type": "token",
        "noise_level": 30000,
        "model_name": "llama3.1_8B-128k",
        "self_evaluation": "no",
        "dataset": "question_datasets/question_answers_pairs.json",
        "file_extension": "xml",
        "duration": 17.4
    },
    {
        "question": "Below which application rate in kg/min is it advised to use the fine application?",
        "expected_answer": "Below 40 kg/min.",
        "model_answer": "The answer is: 9 kg/min.",
        "target_page": 66,
        "context_type": "token",
        "noise_level": 30000,
        "model_name": "llama3.1_8B-128k",
        "self_evaluation": "no",
        "dataset": "question_datasets/question_answers_pairs.json",
        "file_extension": "xml",
        "duration": 15.8
    },
    {
        "question": "What is the general formula for calculating the required flowrate of fertilizer in kg/min?",
        "expected_answer": "Working width (m) x Driving speed (km/h) x Application rate (kg/ha) / 600",
        "model_answer": "The general formula to calculate the required flow rate of fertilizer is:\n\nBen\u00f6tigte Auslassgeschwindigkeit (kg/min) = Arbeitsbreite (m) x Fahrgeschwindigkeit (km/h) x Ausbringmenge (kg/ha)\n\nThis formula can be used for all types of fertilizers, not just ExactLine.",
        "target_page": 68,
        "context_type": "token",
        "noise_level": 30000,
        "model_name": "llama3.1_8B-128k",
        "self_evaluation": "no",
        "dataset": "question_datasets/question_answers_pairs.json",
        "file_extension": "xml",
        "duration": 16.7
    },
    {
        "question": "What type of serial connection does the IsoMatch control box use for communication?",
        "expected_answer": "RS 232",
        "model_answer": "The IsoMatch control box uses a RS 232-connection (Serielle Anschluss) for communication.",
        "target_page": 72,
        "context_type": "token",
        "noise_level": 30000,
        "model_name": "llama3.1_8B-128k",
        "self_evaluation": "yes",
        "dataset": "question_datasets/question_answers_pairs.json",
        "file_extension": "xml",
        "duration": 16.0
    },
    {
        "question": "When loading manually, what's the maximum distance in mm between the hopper rim and the ground before a platform is mandatory?",
        "expected_answer": "1250 mm",
        "model_answer": "The answer to this question can be found on page 73 of the manual. The maximum distance between the hopper rim and the ground before a platform is 1250 mm.",
        "target_page": 74,
        "context_type": "token",
        "noise_level": 30000,
        "model_name": "llama3.1_8B-128k",
        "self_evaluation": "yes",
        "dataset": "question_datasets/question_answers_pairs.json",
        "file_extension": "xml",
        "duration": 16.2
    },
    {
        "question": "What is the maximum distance in mm between spreader and loading platform?",
        "expected_answer": "200 mm maximum distance between them.",
        "model_answer": "The answer to this question can be found on page 36 of the manual. The maximum distance is 200 mm.",
        "target_page": 74,
        "context_type": "token",
        "noise_level": 30000,
        "model_name": "llama3.1_8B-128k",
        "self_evaluation": "yes",
        "dataset": "question_datasets/question_answers_pairs.json",
        "file_extension": "xml",
        "duration": 0.6
    },
    {
        "question": "What does a tray test check on a fertilizer spreader?",
        "expected_answer": "Fertilizer distribution pattern of the spreader.",
        "model_answer": "A tray test is not mentioned in the provided text. However, I can infer from the context that you are referring to a \"Streumengentest\" or \"Streubildkontrolle\", which is a test of the fertilizer spreader's performance.\n\nThe correct answer is: A Streumengentest (or Streubildkontrolle) is performed by checking if the fertilizer is spread evenly and correctly, with no gaps or overlaps.",
        "target_page": 76,
        "context_type": "token",
        "noise_level": 30000,
        "model_name": "llama3.1_8B-128k",
        "self_evaluation": "no",
        "dataset": "question_datasets/question_answers_pairs.json",
        "file_extension": "xml",
        "duration": 17.1
    },
    {
        "question": "What materials are required to perform the tray test?",
        "expected_answer": "A measuring tape or ruler, a spirit level, 7 troughs, 7 graduated tubes, a funnel, a notebook, pen, calculator, this manual, and the software's instruction manual.",
        "model_answer": "The text does not explicitly state what materials are required for the tray test. However, based on the context, it can be inferred that the following materials are necessary:\n\n* Auffangbeh\u00e4lter (Auffangbeh\u00e4lter) - a container to hold the material\n* Messrohre (Messr\u00f6hrchen) - measuring tubes\n* Trichter (Trichter) - a tool for cleaning the measuring tubes\n* Notizblock, Stift und Taschenrechner (Notizbuch, Stift und Taschenrechner) - a notebook and writing instrument to record measurements\n* Bedienungsanleitung der Software (Bedienungsanleitung) - the user manual of the software\n\nThese materials are necessary for performing the tray test.",
        "target_page": 77,
        "context_type": "token",
        "noise_level": 30000,
        "model_name": "llama3.1_8B-128k",
        "self_evaluation": "no",
        "dataset": "question_datasets/question_answers_pairs.json",
        "file_extension": "xml",
        "duration": 18.1
    },
    {
        "question": "What maximum wind speed in m/s is permissible for both the tray test and actual spreading?",
        "expected_answer": "3 m/s)",
        "model_answer": "The maximum wind speed in m/s for both the tray test and actual spreading with ExactLine is 3 m/s.",
        "target_page": 77,
        "context_type": "token",
        "noise_level": 30000,
        "model_name": "llama3.1_8B-128k",
        "self_evaluation": "yes",
        "dataset": "question_datasets/question_answers_pairs.json",
        "file_extension": "xml",
        "duration": 0.6
    },
    {
        "question": "What is the required height of the spreading disc above the troughs for one-sided boundary spreading?",
        "expected_answer": "75 cm above the troughs.",
        "model_answer": "The required height of the spreading disc above the troughs for one-sided boundary spreading is 75 cm.",
        "target_page": 84,
        "context_type": "token",
        "noise_level": 30000,
        "model_name": "llama3.1_8B-128k",
        "self_evaluation": "yes",
        "dataset": "question_datasets/question_answers_pairs.json",
        "file_extension": "xml",
        "duration": 16.0
    },
    {
        "question": "Before testing the ExactLine spreading pattern, what specific height in cm should the spreading disc be set to above the troughs?",
        "expected_answer": "75 cm",
        "model_answer": "The correct answer is: 75cm.",
        "target_page": 89,
        "context_type": "token",
        "noise_level": 30000,
        "model_name": "llama3.1_8B-128k",
        "self_evaluation": "yes",
        "dataset": "question_datasets/question_answers_pairs.json",
        "file_extension": "xml",
        "duration": 15.8
    },
    {
        "question": "What is the maximum fertilizer loss of the quantity in the middle trough in percent allowed in an imaginative ditch?",
        "expected_answer": "10% of the quantity in the middle trough",
        "model_answer": "The maximum fertilizer loss of the quantity in the middle trough in percent is 10%.",
        "target_page": 91,
        "context_type": "token",
        "noise_level": 30000,
        "model_name": "llama3.1_8B-128k",
        "self_evaluation": "yes",
        "dataset": "question_datasets/question_answers_pairs.json",
        "file_extension": "xml",
        "duration": 15.9
    },
    {
        "question": "After disengaging the PTO shaft, what poses a continued danger and why?",
        "expected_answer": "Inertia causes continued rotation.",
        "model_answer": "The answer is: \"Der Zapfwelle l\u00e4uft nach Ausschalten nach.\"",
        "target_page": 94,
        "context_type": "token",
        "noise_level": 30000,
        "model_name": "llama3.1_8B-128k",
        "self_evaluation": "yes",
        "dataset": "question_datasets/question_answers_pairs.json",
        "file_extension": "xml",
        "duration": 15.9
    },
    {
        "question": "According to the last setting check, what is the recommended height in centimeter of the spreader over the ground or crops?",
        "expected_answer": "75 cm",
        "model_answer": "The recommended height for the spreader over the ground or crops is 75 cm.",
        "target_page": 96,
        "context_type": "token",
        "noise_level": 30000,
        "model_name": "llama3.1_8B-128k",
        "self_evaluation": "yes",
        "dataset": "question_datasets/question_answers_pairs.json",
        "file_extension": "xml",
        "duration": 15.9
    },
    {
        "question": "What happens when hopper content falls below 100 kg?",
        "expected_answer": "Automatic calibration switches off.",
        "model_answer": "The answer is: \"Die automatische Kalibrierung wird ausgeschaltet.\"",
        "target_page": 101,
        "context_type": "token",
        "noise_level": 30000,
        "model_name": "llama3.1_8B-128k",
        "self_evaluation": "yes",
        "dataset": "question_datasets/question_answers_pairs.json",
        "file_extension": "xml",
        "duration": 15.9
    },
    {
        "question": "What are the two functions for border spreading?",
        "expected_answer": "Hydraulic border spreading plate and ExactLine.",
        "model_answer": "The two functions for border spreading are:\n\n1. Einscheiben-Grenzstreuen mit dem hydraulischen Grenzstreublech (Zubeh\u00f6r)\n2. Zweischeiben-Grenzstreuen mit ExactLine.\n\nThese are the two functions for border spreading mentioned in the text.",
        "target_page": 106,
        "context_type": "token",
        "noise_level": 30000,
        "model_name": "llama3.1_8B-128k",
        "self_evaluation": "yes",
        "dataset": "question_datasets/question_answers_pairs.json",
        "file_extension": "xml",
        "duration": 16.6
    },
    {
        "question": "What two actions must be done in the event of spreader failure or stoppage while using the spreader in the field?",
        "expected_answer": " Stop spreading immediately and disconnect the PTO shaft immediately.",
        "model_answer": "The two actions to be taken in case of spreader failure or stoppage are:\n\n1. Stop the spreader immediately.\n2. Shut off the powertrain.\n\nThese actions should be done carefully to prevent accidents and injuries.",
        "target_page": 108,
        "context_type": "token",
        "noise_level": 30000,
        "model_name": "llama3.1_8B-128k",
        "self_evaluation": "no",
        "dataset": "question_datasets/question_answers_pairs.json",
        "file_extension": "xml",
        "duration": 16.4
    },
    {
        "question": "What should you do if a spreading disc spreads irregularly?",
        "expected_answer": "Stop spreading and disconnect the PTO shaft immediately.",
        "model_answer": "If a spreading disc is spreading irregularly, you should:\n\n1. Check the dosing system to ensure it's set up correctly.\n2. Check if the spreader is properly aligned with the field.\n3. Check the position of the dosing points on both sides.\n4. If necessary, adjust the position of the dosing points.\n\nThis answer is based on the provided text, which seems to be a manual for a machine used in agriculture.",
        "target_page": 113,
        "context_type": "token",
        "noise_level": 30000,
        "model_name": "llama3.1_8B-128k",
        "self_evaluation": "no",
        "dataset": "question_datasets/question_answers_pairs.json",
        "file_extension": "xml",
        "duration": 17.1
    },
    {
        "question": "What is the maximum allowable temperature in degrees celsius when cleaning the machine with water or steam?",
        "expected_answer": "40 degrees Celsius",
        "model_answer": "The maximum allowable temperature for cleaning the machine with water or steam is 40\u00b0C.",
        "target_page": 117,
        "context_type": "token",
        "noise_level": 30000,
        "model_name": "llama3.1_8B-128k",
        "self_evaluation": "yes",
        "dataset": "question_datasets/question_answers_pairs.json",
        "file_extension": "xml",
        "duration": 15.9
    },
    {
        "question": "What is the maximum allowable pressure in bar when cleaning the machine with water or steam?",
        "expected_answer": "80 bar",
        "model_answer": "The maximum allowable pressure for cleaning the machine with water or steam is 80 bar.",
        "target_page": 117,
        "context_type": "token",
        "noise_level": 30000,
        "model_name": "llama3.1_8B-128k",
        "self_evaluation": "yes",
        "dataset": "question_datasets/question_answers_pairs.json",
        "file_extension": "xml",
        "duration": 0.5
    },
    {
        "question": "What specific precaution should be taken regarding white metal parts to prevent corrosion during winter storage?",
        "expected_answer": "Preservative grease or preserving liquid.",
        "model_answer": "The text does not provide a direct answer to the question. However, I can infer an answer based on the context.\n\nTo prevent corrosion of white metal parts during winter storage, you should:\n\n* Use a protective coating or paint that is specifically designed for protecting against corrosion.\n* Store the machine in a dry place with good ventilation.\n* Keep the machine away from salt and moisture.\n* Regularly check the machine's components, especially the moving parts, to ensure they are not damaged by rust.\n\nThe text does not provide specific information about the type of protective coating or paint that should be used.",
        "target_page": 121,
        "context_type": "token",
        "noise_level": 30000,
        "model_name": "llama3.1_8B-128k",
        "self_evaluation": "no",
        "dataset": "question_datasets/question_answers_pairs.json",
        "file_extension": "xml",
        "duration": 17.5
    },
    {
        "question": "What specific precaution should be taken before welding on the machine after using nitrate-containing fertilizer?",
        "expected_answer": "Remove all fertilizer remnants.",
        "model_answer": "The correct answer is: \"Vermeiden Sie den Kontakt mit sch\u00e4dlichen Mitteln\" (Beim Arbeiten am Streuer kommen Sie wahrscheinlich in Kontakt mit Kunstd\u00fcnger und anderen Mitteln, die Sie ausstreuen m\u00f6chten. Tragen Sie Schutzkleidung und Sicherheitshandschuhe, lesen Sie die Sicherheitsanweisungen des Lieferanten und befolgen Sie die zus\u00e4tzliche Hinweise.\"",
        "target_page": 123,
        "context_type": "token",
        "noise_level": 30000,
        "model_name": "llama3.1_8B-128k",
        "self_evaluation": "no",
        "dataset": "question_datasets/question_answers_pairs.json",
        "file_extension": "xml",
        "duration": 17.1
    },
    {
        "question": "How many grease nipples do the discharge bushings have?",
        "expected_answer": "Two grease nipples per discharge bushing.",
        "model_answer": "The answer is: 2.",
        "target_page": 126,
        "context_type": "token",
        "noise_level": 30000,
        "model_name": "llama3.1_8B-128k",
        "self_evaluation": "yes",
        "dataset": "question_datasets/question_answers_pairs.json",
        "file_extension": "xml",
        "duration": 15.7
    },
    {
        "question": "What is the required grease level in mm below the filler opening for spreading disc gearboxes after the machine has stood still?",
        "expected_answer": "35 mm",
        "model_answer": "The required grease level is 35mm.",
        "target_page": 127,
        "context_type": "token",
        "noise_level": 30000,
        "model_name": "llama3.1_8B-128k",
        "self_evaluation": "yes",
        "dataset": "question_datasets/question_answers_pairs.json",
        "file_extension": "xml",
        "duration": 15.8
    },
    {
        "question": "What is the maximum hydraulic pressure allowed for the hydaulic system in bars?",
        "expected_answer": "210 bars.",
        "model_answer": "The maximum hydraulic pressure allowed for the hydraulic system is 210 bar.",
        "target_page": 131,
        "context_type": "token",
        "noise_level": 30000,
        "model_name": "llama3.1_8B-128k",
        "self_evaluation": "yes",
        "dataset": "question_datasets/question_answers_pairs.json",
        "file_extension": "xml",
        "duration": 15.9
    },
    {
        "question": "What is the required distance in mm between the rope and discharge bushing opening?",
        "expected_answer": "109 mm.",
        "model_answer": "The answer to this question can be found on page 137 of the provided text. The required distance is 1.0 mm.",
        "target_page": 136,
        "context_type": "token",
        "noise_level": 30000,
        "model_name": "llama3.1_8B-128k",
        "self_evaluation": "no",
        "dataset": "question_datasets/question_answers_pairs.json",
        "file_extension": "xml",
        "duration": 16.1
    },
    {
        "question": "What is the required distance in m between the discharge bushing and spreading disc?",
        "expected_answer": "The required distance is 1.0 mm.",
        "model_answer": "The answer to this question can be found on page 137 of the provided text. The required distance is 109 mm.",
        "target_page": 138,
        "context_type": "token",
        "noise_level": 30000,
        "model_name": "llama3.1_8B-128k",
        "self_evaluation": "no",
        "dataset": "question_datasets/question_answers_pairs.json",
        "file_extension": "xml",
        "duration": 16.1
    },
    {
        "question": "How often should the agitator axle seal be replaced?",
        "expected_answer": "Every season and after every 100 operational hours.",
        "model_answer": "The text does not explicitly state how often the agitator axle seal should be replaced. However, based on general guidelines for maintenance of agricultural machinery, it is recommended to replace the agitator axle seal every 1000 hours or when it shows signs of wear and tear.\n\nIn the provided text, there are several references to replacing seals in general, but not specifically for the agitator axle seal. For example:\n\n* \"Tauschen Sie die Kunststoffdichtring aus.\" (page 140)\n* \"Tauschen Sie R\u00fchrerwelle und/oder den R\u00fchrer aus.\" (page 140)\n\nThese statements suggest that seals should be replaced when they show signs of wear and tear, but do not specify a specific time frame.",
        "target_page": 140,
        "context_type": "token",
        "noise_level": 30000,
        "model_name": "llama3.1_8B-128k",
        "self_evaluation": "no",
        "dataset": "question_datasets/question_answers_pairs.json",
        "file_extension": "xml",
        "duration": 18.1
    },
    {
        "question": "What is the pattern of the type 'mineral'?",
        "expected_answer": "angular, with sharp angles and edges",
        "model_answer": "The pattern for the type \"Mineralisch\" is: eckig, mit scharfen Kanten und R\u00e4ndern.",
        "target_page": 58,
        "context_type": "token",
        "noise_level": 30000,
        "model_name": "llama3.1_8B-128k",
        "self_evaluation": "yes",
        "dataset": "question_datasets/question_answers_tables.json",
        "file_extension": "xml",
        "duration": 16.1
    },
    {
        "question": "What is the hopper weight without hopper cover in kg of the Exacta-TLX GEOSPREAD 3225?",
        "expected_answer": "337.5 kg",
        "model_answer": "The answer is: 765.",
        "target_page": 36,
        "context_type": "token",
        "noise_level": 30000,
        "model_name": "llama3.1_8B-128k",
        "self_evaluation": "no",
        "dataset": "question_datasets/question_answers_tables.json",
        "file_extension": "xml",
        "duration": 15.8
    },
    {
        "question": "What is the weight in kg of the Exacta-TLX GEOSPREAD 3900?",
        "expected_answer": "795 kg",
        "model_answer": "The weight of the Exacta-TLX-GEOSPREAD 3900 is 4895 kg.",
        "target_page": 36,
        "context_type": "token",
        "noise_level": 30000,
        "model_name": "llama3.1_8B-128k",
        "self_evaluation": "no",
        "dataset": "question_datasets/question_answers_tables.json",
        "file_extension": "xml",
        "duration": 0.6
    },
    {
        "question": "What is the sound level in dB of a Tractor + spreading spreader (Kali 60) with its rear window opened?",
        "expected_answer": "84.6 dB",
        "model_answer": "The sound level of a tractor + spreading spreader (Kali 60) with its rear window open is 73.0 dB.",
        "target_page": 37,
        "context_type": "token",
        "noise_level": 30000,
        "model_name": "llama3.1_8B-128k",
        "self_evaluation": "no",
        "dataset": "question_datasets/question_answers_tables.json",
        "file_extension": "xml",
        "duration": 16.1
    },
    {
        "question": "How often (in what interval) must the condition of the vanes be inspected?",
        "expected_answer": "daily",
        "model_answer": "The answer is: \"After 10 Betriebsstunden\"",
        "target_page": 125,
        "context_type": "token",
        "noise_level": 30000,
        "model_name": "llama3.1_8B-128k",
        "self_evaluation": "no",
        "dataset": "question_datasets/question_answers_tables.json",
        "file_extension": "xml",
        "duration": 15.9
    },
    {
        "question": "How often (in what interval) must the bushing height be checked and the discharge be set?",
        "expected_answer": "after the first 10 hours and every 100 hours, but a minimum of once per year",
        "model_answer": "The bushing height should be checked every 100 betriebsstunden (betriebliche Stunden) or after each season.",
        "target_page": 125,
        "context_type": "token",
        "noise_level": 30000,
        "model_name": "llama3.1_8B-128k",
        "self_evaluation": "no",
        "dataset": "question_datasets/question_answers_tables.json",
        "file_extension": "xml",
        "duration": 0.7
    },
    {
        "question": "How often (in what interval) must the agitator seal be replaced?",
        "expected_answer": "every 100 hours or if worn",
        "model_answer": "The answer is not explicitly stated in the provided text. However, based on the context, I can infer that the agitator seal must be replaced every 10 betriebsstunden (betriebliche Stunden) or after every 100 betriebsstunden (betriebliche Stunden).",
        "target_page": 125,
        "context_type": "token",
        "noise_level": 30000,
        "model_name": "llama3.1_8B-128k",
        "self_evaluation": "no",
        "dataset": "question_datasets/question_answers_tables.json",
        "file_extension": "xml",
        "duration": 1.2
    },
    {
        "question": "With what torque in Nm must a M18 hexagon steel bolt with a 10.9 quality and with a 0.13 friction be fastened?",
        "expected_answer": "420 Nm",
        "model_answer": "The answer is: M18 = 12.9",
        "target_page": 129,
        "context_type": "token",
        "noise_level": 30000,
        "model_name": "llama3.1_8B-128k",
        "self_evaluation": "no",
        "dataset": "question_datasets/question_answers_tables.json",
        "file_extension": "xml",
        "duration": 15.9
    },
    {
        "question": "With what torque in Nm must a M6 hexagon stainless steel bolt with a 70 (A2) quality and with a 0.2 friction be fastened?",
        "expected_answer": "9.9 Nm",
        "model_answer": "The answer is: M10 = 29.9 Nm",
        "target_page": 129,
        "context_type": "token",
        "noise_level": 30000,
        "model_name": "llama3.1_8B-128k",
        "self_evaluation": "no",
        "dataset": "question_datasets/question_answers_tables.json",
        "file_extension": "xml",
        "duration": 0.5
    },
    {
        "question": "What should I do if the flow of the fertiliser is blocked, at what page should I look?",
        "expected_answer": "Clean the machine well after each use. Replace the agitator if it is worn out. The page is 118",
        "model_answer": "The answer to your question can be found on page 118.",
        "target_page": 152,
        "context_type": "token",
        "noise_level": 30000,
        "model_name": "llama3.1_8B-128k",
        "self_evaluation": "yes",
        "dataset": "question_datasets/question_answers_tables.json",
        "file_extension": "xml",
        "duration": 15.9
    },
    {
        "question": "How much extra diesel does the tractor consume to use the Exacta-TLX GEOSPREAD?",
        "expected_answer": "Not found in context",
        "model_answer": "The text does not provide a clear answer to the question. However, I can try to help you find the answer.\n\nAccording to the provided text, the Exacta-TLX-GEOSPREAD is a system that allows forageable products such as manure and seeds to be spread evenly over the field. It has two sieves with 8 arms each, which are flat mounted so that the fertilizer flows in a constant horizontal flow through them.\n\nThe tractor's consumption of diesel fuel is not mentioned in the provided text.",
        "target_page": 23,
        "context_type": "token",
        "noise_level": 30000,
        "model_name": "llama3.1_8B-128k",
        "self_evaluation": "yes",
        "dataset": "question_datasets/question_answers_unanswerable.json",
        "file_extension": "xml",
        "duration": 17.3
    },
    {
        "question": "Is fine application more expensive than normal dosing?",
        "expected_answer": "Not found in context",
        "model_answer": "The answer is not explicitly stated in the text. However, based on the context, I can infer that the correct answer to the question \"Is fine application more expensive than normal dosing?\" is:\n\nNormal dosing is generally less expensive than fine application.\n\nIn the provided text, it is mentioned that for large working widths, a special axle set (Schaufelsatz) is required. This suggests that fine application requires additional equipment or components, which would increase its cost compared to normal dosing.\n\nAdditionally, in the section on \"Schutzbleche\" (page 45), it is mentioned that a safety bracket (Trittstufe) is available for the machine, which could be an additional expense.",
        "target_page": 24,
        "context_type": "token",
        "noise_level": 30000,
        "model_name": "llama3.1_8B-128k",
        "self_evaluation": "no",
        "dataset": "question_datasets/question_answers_unanswerable.json",
        "file_extension": "xml",
        "duration": 2.5
    },
    {
        "question": "Is one-sided boundary spreading suitable for small gardens?",
        "expected_answer": "Not found in context",
        "model_answer": "The text does not provide a direct answer to the question \"Is one-sided boundary spreading suitable for small gardens?\" but it provides information about the machine's technical data. The table on page 36 lists various specifications of the Exacta-TLX-GEOSPREAD, which includes the maximum weight of the machine with and without an Abdeckplane (electrical cover).",
        "target_page": 28,
        "context_type": "token",
        "noise_level": 30000,
        "model_name": "llama3.1_8B-128k",
        "self_evaluation": "no",
        "dataset": "question_datasets/question_answers_unanswerable.json",
        "file_extension": "xml",
        "duration": 16.8
    },
    {
        "question": "For what other kind of connections can the IM Tellus Input cable be used?",
        "expected_answer": "Not found in context",
        "model_answer": "The text does not explicitly state which type of connection the \"IM Tellus input\" cable can be used for. However, based on the context, it is likely referring to a 9-pole CAN (Controller Area Network) cable.",
        "target_page": 32,
        "context_type": "token",
        "noise_level": 30000,
        "model_name": "llama3.1_8B-128k",
        "self_evaluation": "no",
        "dataset": "question_datasets/question_answers_unanswerable.json",
        "file_extension": "xml",
        "duration": 16.4
    },
    {
        "question": "Can the IsoMatch universal ISOBUS terminal be used to check the weather?",
        "expected_answer": "Not found in context",
        "model_answer": "The IsoMatch universal ISOBUS terminal is not used for checking the weather.",
        "target_page": 33,
        "context_type": "token",
        "noise_level": 30000,
        "model_name": "llama3.1_8B-128k",
        "self_evaluation": "no",
        "dataset": "question_datasets/question_answers_unanswerable.json",
        "file_extension": "xml",
        "duration": 15.9
    },
    {
        "question": "Can IsoMatch Tellus be connected to an external mouse?",
        "expected_answer": "Not found in context",
        "model_answer": "The answer is not explicitly stated in the provided text. However, based on the context, I can infer that IsoMatch Tellus cannot be connected to an external mouse.\n\nThe text mentions \"ISOMatch Terminal\" and \"Bedienpult\", which are related to the IsoMatch system, but it does not mention anything about connecting it to a mouse.",
        "target_page": 34,
        "context_type": "token",
        "noise_level": 30000,
        "model_name": "llama3.1_8B-128k",
        "self_evaluation": "no",
        "dataset": "question_datasets/question_answers_unanswerable.json",
        "file_extension": "xml",
        "duration": 16.8
    },
    {
        "question": "Is the Hydraulic border spreading plate made out of steel?",
        "expected_answer": "Not found in context",
        "model_answer": "The text does not explicitly state whether the hydraulic border spreading plate is made of steel.",
        "target_page": 47,
        "context_type": "token",
        "noise_level": 30000,
        "model_name": "llama3.1_8B-128k",
        "self_evaluation": "no",
        "dataset": "question_datasets/question_answers_unanswerable.json",
        "file_extension": "xml",
        "duration": 15.9
    },
    {
        "question": "Can the linkage pin for the tractor be made out of aluminium?",
        "expected_answer": "Not found in context",
        "model_answer": "The text does not explicitly state whether the linkage pin can be made of aluminum. However, based on the context, we can infer that the answer is no.\n\nThe text mentions \"Schutzrohre\" (protective sleeve) which is made of steel and is used to protect the Gelenkwelle from damage. It also mentions \"Sicherungsketten\" (safety chains) which are used to prevent the protective sleeve from rotating with the Gelenkwelle.\n\nThe text does not mention aluminum as a material for the linkage pin, but it does imply that the linkage is made of steel or another metal, given the context.",
        "target_page": 53,
        "context_type": "token",
        "noise_level": 30000,
        "model_name": "llama3.1_8B-128k",
        "self_evaluation": "no",
        "dataset": "question_datasets/question_answers_unanswerable.json",
        "file_extension": "xml",
        "duration": 17.7
    },
    {
        "question": "Can the tray test be performed at 40 degrees Celsius?",
        "expected_answer": "Not found in context",
        "model_answer": "The answer is not explicitly stated in the provided text. However, based on the context, we can infer that the tray test should be performed at a temperature of 40 degrees Celsius.\n\nThe relevant passage from the text is:\n\n\"Beim Gebrauch der ExactLine beabsichtigen Sie eine maximale Anf\u00fcllung zum Rand hin, jedoch bei einem minimalen Verlust im Graben. Testen Sie daher die Funktion der ExactLine. F\u00fchren Sie den Test nicht am Grabenrand aus, sondern markieren Sie eine Linie, hinter der sich der fiktive Grabenrand befindet.\"\n\nThis passage suggests that the tray test should be performed at a temperature of 40 degrees Celsius, as it is mentioned as an option for testing the ExactLine.",
        "target_page": 77,
        "context_type": "token",
        "noise_level": 30000,
        "model_name": "llama3.1_8B-128k",
        "self_evaluation": "no",
        "dataset": "question_datasets/question_answers_unanswerable.json",
        "file_extension": "xml",
        "duration": 18.1
    },
    {
        "question": "Can the hydraulic border spreading plate be actuated pneumatically?",
        "expected_answer": "Not found in context",
        "model_answer": "The answer is: No.",
        "target_page": 85,
        "context_type": "token",
        "noise_level": 30000,
        "model_name": "llama3.1_8B-128k",
        "self_evaluation": "no",
        "dataset": "question_datasets/question_answers_unanswerable.json",
        "file_extension": "xml",
        "duration": 15.7
    },
    {
        "question": "By which environmental standards is the maximum acceptable loss in the ditch is determined?",
        "expected_answer": "Not found in context",
        "model_answer": "The maximum acceptable loss in the ditch is 10% of the amount of fertilizer applied.",
        "target_page": 87,
        "context_type": "token",
        "noise_level": 30000,
        "model_name": "llama3.1_8B-128k",
        "self_evaluation": "no",
        "dataset": "question_datasets/question_answers_unanswerable.json",
        "file_extension": "xml",
        "duration": 15.9
    },
    {
        "question": "How should one proceed to stop spreading the fertilizer?",
        "expected_answer": "Not found in context",
        "model_answer": "The answer is not explicitly stated in the provided text. However, based on the context, I can infer a step-by-step guide to stop spreading fertilizer:\n\n1. Check if the dosing system is functioning correctly.\n2. If the dosing system is faulty, shut off the machine and check for any blockages or obstructions that may be causing the problem.\n3. Check the condition of the siebe (sieve) and clean it thoroughly.\n4. Check the condition of the dosiermechanismus (dosing mechanism) and adjust as necessary.\n5. Check the height of the streuer (spreader) and make sure it is set to 75 cm above the ground or the erntegut (crop).\n6. Make sure the correct dosing system is selected in the control panel.\n7. Start the machine and check if the fertilizer is being spread evenly.\n\nIf you are using a ExactLine, follow these steps:\n\n1. Bring the ExactLine into working position by operating the hydraulic steering gear for a few seconds.\n2. Check that the ExactLine symbol is displayed on the display.\n3. Make sure the correct dosing system is selected in the control panel.\n4. Start the machine and set the correct speed of the spreader (streuer) according to the table.\n\nIf you are using a hydraulische Grenzstreublech, follow these steps:\n\n1. Set the hydraulische Grenzstreublech to the correct position.\n2. Check that the Schaufeln do not touch the Grenzstreublech.\n3. Make sure the correct dosing system is selected in the control panel.\n4. Start the machine and set the correct speed of the spreader (streuer) according to the table.\n\nIf you are using a ExactLine, follow these steps:\n\n1. Bring the ExactLine into working position by operating the hydraulic steering gear for a few seconds.\n2. Check that the ExactLine symbol is displayed on the display.\n3. Make sure the correct dosing system is selected in the control panel.\n4. Start the machine and set the correct speed of the spreader (streuer) according to the table.\n\nIf you are using a hydraulische Grenzstreublech, follow these steps:\n\n1. Set the hydraulische Grenzstreublech to the correct position.\n2. Check that the Schaufeln do not touch the Grenzstreublech.\n3. Make sure the correct dosing system is selected in the control panel.\n4. Start the machine and set the correct speed of the spreader (streuer) according to the table.\n\nIf you are using a ExactLine, follow these steps:\n\n1. Bring the ExactLine into working position by operating the hydraulic steering gear for a few seconds.\n2. Check that the ExactLine symbol is displayed on the display.\n3. Make sure the correct dosing system is selected in the control panel.\n4. Start the machine and set the correct speed of the spreader (streuer) according to the table.\n\nIf you are using a hydraulische Grenzstreublech, follow these steps:\n\n1. Set the hydraulische Grenzstreublech to the correct position.\n2. Check that the Schaufeln do not touch the Grenzstreublech.\n3. Make sure the correct dosing system is selected in the control panel.\n4. Start the machine and set the correct speed of the spreader (streuer) according to the table.\n\nIf you are using a ExactLine, follow these steps:\n\n1. Bring the ExactLine into working position by operating the hydraulic steering gear for a few seconds.\n2. Check that the ExactLine symbol is displayed on the display.\n3. Make sure the correct dosing system is selected in the control panel.\n4. Start the machine and set the correct speed of the spreader (streuer) according to the table.\n\nIf you are using a hydraulische Grenzstreublech, follow these steps:\n\n1. Set the hydraulische Grenzstreublech to the correct position.\n2. Check that the Schaufeln do not touch the Grenzstreublech.\n3. Make sure the correct dosing system is selected in the control panel.\n4. Start the machine and set the correct speed of the spreader (streuer) according to the table.\n\nIf you are using a ExactLine, follow these steps:\n\n1. Bring the ExactLine into working position by operating the hydraulic steering gear for a few seconds.\n2. Check that the ExactLine symbol is displayed on the display.\n3. Make sure the correct dosing system is selected in the control panel.\n4. Start the machine and set the correct speed of the spreader (streuer) according to the table.\n\nIf you are using a hydraulische Grenzstreublech, follow these steps:\n\n1. Set the hydraulische Grenzstreublech to the correct position.\n2. Check that the Schaufeln do not touch the Grenzstreublech",
        "target_page": 100,
        "context_type": "token",
        "noise_level": 30000,
        "model_name": "llama3.1_8B-128k",
        "self_evaluation": "no",
        "dataset": "question_datasets/question_answers_unanswerable.json",
        "file_extension": "xml",
        "duration": 31.7
    },
    {
        "question": "What is the maximum height the fertilizer flies when spreading without GEOCONTROL headland",
        "expected_answer": "Not found in context",
        "model_answer": "The maximum height the fertilizer flies when spreading without using the GEOCONTROL system is 75 cm.",
        "target_page": 103,
        "context_type": "token",
        "noise_level": 30000,
        "model_name": "llama3.1_8B-128k",
        "self_evaluation": "no",
        "dataset": "question_datasets/question_answers_unanswerable.json",
        "file_extension": "xml",
        "duration": 16.0
    },
    {
        "question": "What is seven-sided boundary spreading with the hydraulicborder spreading plate?",
        "expected_answer": "Not found in context",
        "model_answer": "The answer to this question is not explicitly stated in the provided text. However, based on the context, I can infer that the question is asking about the correct way to position the dosiermechanismus (dosiermechanism) when performing seven-sided boundary spreading with a hydraulic border spreading plate.\n\nFrom the text, it appears that the dosiermechanismus must be positioned in the middle over the streuscheiben.",
        "target_page": 107,
        "context_type": "token",
        "noise_level": 30000,
        "model_name": "llama3.1_8B-128k",
        "self_evaluation": "no",
        "dataset": "question_datasets/question_answers_unanswerable.json",
        "file_extension": "xml",
        "duration": 17.0
    },
    {
        "question": "Which appropriate measures for road transport should be taken when stopping work?",
        "expected_answer": "Not found in context",
        "model_answer": "The text does not provide a clear answer to the question. However, based on the context, I can infer some general guidelines for road transport.\n\nWhen stopping work with the machine, you should:\n\n1. Shut off the dosing units.\n2. Turn off the hydraulic system.\n3. Switch off the control panel.\n4. Remove the key from the ignition switch.\n5. Engage the parking brake.\n6. Ensure that all parts of the machine are stationary before proceeding.\n\nThese steps will help prevent accidents and ensure a safe stoppage.",
        "target_page": 112,
        "context_type": "token",
        "noise_level": 30000,
        "model_name": "llama3.1_8B-128k",
        "self_evaluation": "no",
        "dataset": "question_datasets/question_answers_unanswerable.json",
        "file_extension": "xml",
        "duration": 17.4
    },
    {
        "question": "Why do most types of fertiliser attract water?",
        "expected_answer": "Not found in context",
        "model_answer": "Fertilizers can attract water due to their chemical properties.",
        "target_page": 114,
        "context_type": "token",
        "noise_level": 30000,
        "model_name": "llama3.1_8B-128k",
        "self_evaluation": "yes",
        "dataset": "question_datasets/question_answers_unanswerable.json",
        "file_extension": "xml",
        "duration": 15.9
    },
    {
        "question": "Why is damage to the vanes, spreading disc or discharge bushing, most likely caused by a hard object?",
        "expected_answer": "Not found in context",
        "model_answer": "The text does not explicitly state what the damage to the vanes is. However, based on the context, it can be inferred that the damage is most likely caused by a hard object blocking or obstructing the discharge bushing.",
        "target_page": 115,
        "context_type": "token",
        "noise_level": 30000,
        "model_name": "llama3.1_8B-128k",
        "self_evaluation": "no",
        "dataset": "question_datasets/question_answers_unanswerable.json",
        "file_extension": "xml",
        "duration": 16.4
    },
    {
        "question": "What should a person do who fell into the fertilizer and no physician is available?",
        "expected_answer": "Not found in context",
        "model_answer": "The answer to this question is not explicitly stated in the provided text. However, based on the context, I can infer a general guideline for the situation.\n\nIf someone falls into the fertilizer and no physician is available, they should:\n\n1. Call 112 (the emergency number) or contact a nearby hospital or medical facility.\n2. If possible, try to carefully remove the person from the fertilizer while wearing protective gear such as gloves and safety glasses.\n3. If the person is conscious, ask them if they are experiencing any symptoms of poisoning, such as dizziness, nausea, or difficulty breathing.\n4. If the person is unconscious, call 112 (the emergency number) or contact a nearby hospital or medical facility for assistance.\n\nPlease note that this is an inference based on the context and not a direct answer from the provided text.",
        "target_page": 117,
        "context_type": "token",
        "noise_level": 30000,
        "model_name": "llama3.1_8B-128k",
        "self_evaluation": "no",
        "dataset": "question_datasets/question_answers_unanswerable.json",
        "file_extension": "xml",
        "duration": 18.3
    },
    {
        "question": "What happens if the machine grease nipples are never lubricated?",
        "expected_answer": "Not found in context",
        "model_answer": "If the machine grease nipples are not lubricated, they can cause damage to the machine.",
        "target_page": 118,
        "context_type": "token",
        "noise_level": 30000,
        "model_name": "llama3.1_8B-128k",
        "self_evaluation": "no",
        "dataset": "question_datasets/question_answers_unanswerable.json",
        "file_extension": "xml",
        "duration": 16.0
    },
    {
        "question": "What specific paint should be used to paint any damaged paintwork at the end of the season the machine in preparation for winter storage?",
        "expected_answer": "Not found in context",
        "model_answer": "The text does not provide a clear answer to the question. However, based on the context, I will try to infer an answer.\n\nBased on the provided text, it appears that the machine should be painted with a protective coating or primer before winter storage. The text mentions \"Schmieren und \u00f6len Sie alle Punkte nach der Reinigung nochmals zur Konservierung ein\" which suggests that some sort of protective layer is applied to protect the machine from corrosion and wear.\n\nThe text also mentions \"Verwenden Sie beim Austausch lediglich Originalersatzteile\" which implies that only original parts should be used for replacement, but it does not specifically mention paint.",
        "target_page": 121,
        "context_type": "token",
        "noise_level": 30000,
        "model_name": "llama3.1_8B-128k",
        "self_evaluation": "no",
        "dataset": "question_datasets/question_answers_unanswerable.json",
        "file_extension": "xml",
        "duration": 17.8
    },
    {
        "question": "What is the curriculum of the training program agrarians need to complete to be considered competent to operate this machine?",
        "expected_answer": "Not found in context",
        "model_answer": "The text does not provide a clear answer to the question. However, based on the context, I can infer that the curriculum for the training program is likely to include:\n\n1. Familiarity with the machine's technical specifications (e.g., weight, dimensions, operating speed)\n2. Knowledge of the machine's safety features and safety guidelines\n3. Understanding of the machine's operation and maintenance requirements\n4. Training on the use of the machine in different conditions (e.g., varying terrain, weather, soil type)\n\nThe text does not provide a clear answer to the question, but it can be inferred that the training program should cover these topics:\n\n1. Technical specifications of the machine (weight, dimensions, operating speed)\n2. Safety features and safety guidelines\n3. Machine operation and maintenance requirements\n4. Operating the machine in different conditions (various terrain, weather, soil type)\n\nThe text does not provide a clear answer to the question, but it can be inferred that the training program should cover these topics:\n\n1. Technical specifications of the machine (weight, dimensions, operating speed)\n2. Safety features and safety guidelines\n3. Machine operation and maintenance requirements\n4. Operating the machine in different conditions (various terrain, weather, soil type)",
        "target_page": 4,
        "context_type": "token",
        "noise_level": 30000,
        "model_name": "llama3.1_8B-128k",
        "self_evaluation": "no",
        "dataset": "question_datasets/question_answers_unanswerable.json",
        "file_extension": "xml",
        "duration": 19.7
    },
    {
        "question": "By which international standard are the pictograms used in this manual specified for agricultural machinery?",
        "expected_answer": "Not found in context",
        "model_answer": "The pictograms used in this manual are based on the ISO (International Organization for Standardization) standards.",
        "target_page": 5,
        "context_type": "token",
        "noise_level": 30000,
        "model_name": "llama3.1_8B-128k",
        "self_evaluation": "no",
        "dataset": "question_datasets/question_answers_unanswerable.json",
        "file_extension": "xml",
        "duration": 0.6
    },
    {
        "question": "How does the rate of corrosion on the Exacta-TLX GEOSPREAD compare between machines used in coastal vs. inland agricultural regions?",
        "expected_answer": "Not found in context",
        "model_answer": "The text does not provide a clear answer to the question about how the rate of corrosion on the Exacta-TLX GEOSPREAD compares between machines used in coastal vs. inland agricultural regions. The text only mentions that the machine is suitable for use in coastal and land areas, but it does not provide any information about the rate of corrosion.",
        "target_page": 21,
        "context_type": "token",
        "noise_level": 30000,
        "model_name": "llama3.1_8B-128k",
        "self_evaluation": "yes",
        "dataset": "question_datasets/question_answers_unanswerable.json",
        "file_extension": "xml",
        "duration": 1.4
    },
    {
        "question": "What kind of protective safety gloves are needed for cleaning fertiliser remnants from the Exacta-TLX GEOSPREAD before welding?",
        "expected_answer": "Not found in context",
        "model_answer": "The text does not explicitly state what type of protective gloves are needed for cleaning fertilizer remnants from the Exacta-TLX GEOSPREAD before welding. However, based on general safety guidelines, it is recommended to use protective gloves when working with chemicals or materials that can cause skin irritation or damage.\n\nTypically, protective gloves used in this context would be:\n\n* Safety gloves (e.g., mechanic's gloves)\n* Chemical-resistant gloves\n* Protective gloves\n\nThese types of gloves are designed to protect the hands from chemical splashes and spills, as well as cuts and puncture wounds. They can also provide protection against abrasions and cuts.\n\nIt is recommended to choose a glove that fits snugly and has a good grip, with a durable material (e.g., leather or synthetic) and airtightness to prevent liquids from entering the glove.",
        "target_page": 22,
        "context_type": "token",
        "noise_level": 30000,
        "model_name": "llama3.1_8B-128k",
        "self_evaluation": "no",
        "dataset": "question_datasets/question_answers_unanswerable.json",
        "file_extension": "xml",
        "duration": 2.9
    },
    {
        "question": "What are the detailed technical specifications and bandwidth capabilities of different ISOBUS communication protocol versions compatible with the IsoMatch Tellus system?",
        "expected_answer": "Not found in context",
        "model_answer": "The text does not provide a clear answer to the question. It seems to be a manual for a machine with technical specifications and instructions on how to use it safely. The question is about the technical specifications and bandwidth capabilities of different ISOBUS communication protocol versions compatible with the IsoMatch Tellus system.\n\nHowever, I can try to extract some information that might be relevant:\n\nThe text mentions \"ISOBUS-Schlepper\" which suggests that the machine in question is a tractor or agricultural equipment. It also mentions \"GEOCONTROL-Funktionen\", which could refer to a specific feature of the machine related to precision farming.\n\nThe text does not provide any information about different ISOBUS communication protocol versions, but it does mention \"ISOMatch Terminal\" and \"IsoMatch Bedienpult\" which are part of the IsoMatch system. It also mentions \"GEOCONTROL-Funktionen\", which is a feature related to precision farming.\n\nThe text does not provide any information about the technical specifications or bandwidth capabilities of different ISOBUS communication protocol versions, but it does mention \"ISOMatch Terminal\" and \"IsoMatch Bedienpult\" which are part of the IsoMatch system. It also mentions \"GEOCONTROL-Funktionen\", which is a feature related to precision farming.\n\nThe text does not provide any information about different ISOBUS communication protocol versions, but it does mention \"ISOMatch Terminal\" and \"IsoMatch Bedienpult\" which are part of the IsoMatch system. It also mentions \"GEOCONTROL-Funktionen\", which is a feature related to precision farming.\n\nThe text does not provide any information about the technical specifications or bandwidth capabilities of different ISOBUS communication protocol versions, but it does mention \"ISOMatch Terminal\" and \"IsoMatch Bedienpult\" which are part of the IsoMatch system. It also mentions \"GEOCONTROL-Funktionen\", which is a feature related to precision farming.\n\nThe text does not provide any information about different ISOBUS communication protocol versions, but it does mention \"ISOMatch Terminal\" and \"IsoMatch Bedienpult\" which are part of the IsoMatch system. It also mentions \"GEOCONTROL-Funktionen\", which is a feature related to precision farming.\n\nThe text does not provide any information about the technical specifications or bandwidth capabilities of different ISOBUS communication protocol versions, but it does mention \"ISOMatch Terminal\" and \"IsoMatch Bedienpult\" which are part of the IsoMatch system. It also mentions \"GEOCONTROL-Funktionen\", which is a feature related to precision farming.\n\nThe text does not provide any information about different ISOBUS communication protocol versions, but it does mention \"ISOMatch Terminal\" and \"IsoMatch Bedienpult\" which are part of the IsoMatch system. It also mentions \"GEOCONTROL-Funktionen\", which is a feature related to precision farming.\n\nThe text does not provide any information about the technical specifications or bandwidth capabilities of different ISOBUS communication protocol versions, but it does mention \"ISOMatch Terminal\" and \"IsoMatch Bedienpult\" which are part of the IsoMatch system. It also mentions \"GEOCONTROL-Funktionen\", which is a feature related to precision farming.\n\nThe text does not provide any information about different ISOBUS communication protocol versions, but it does mention \"ISOMatch Terminal\" and \"IsoMatch Bedienpult\" which are part of the IsoMatch system. It also mentions \"GEOCONTROL-Funktionen\", which is a feature related to precision farming.\n\nThe text does not provide any information about the technical specifications or bandwidth capabilities of different ISOBUS communication protocol versions, but it does mention \"ISOMatch Terminal\" and \"IsoMatch Bedienpult\" which are part of the IsoMatch system. It also mentions \"GEOCONTROL-Funktionen\", which is a feature related to precision farming.\n\nThe text does not provide any information about different ISOBUS communication protocol versions, but it does mention \"ISOMatch Terminal\" and \"IsoMatch Bedienpult\" which are part of the IsoMatch system. It also mentions \"GEOCONTROL-Funktionen\", which is a feature related to precision farming.\n\nThe text does not provide any information about the technical specifications or bandwidth capabilities of different ISOBUS communication protocol versions, but it does mention \"ISOMatch Terminal\" and \"IsoMatch Bedienpult\" which are part of the IsoMatch system. It also mentions \"GEOCONTROL-Funktionen\", which is a feature related to precision farming.\n\nThe text does not provide any information about different ISOBUS communication protocol versions, but it does mention \"ISOMatch Terminal\" and \"IsoMatch Bedienpult\" which are part of the IsoMatch system. It also mentions \"GEOCONTROL-Funktionen\", which is a feature related to precision farming.\n\nThe text does not provide any information about the technical",
        "target_page": 32,
        "context_type": "token",
        "noise_level": 30000,
        "model_name": "llama3.1_8B-128k",
        "self_evaluation": "no",
        "dataset": "question_datasets/question_answers_unanswerable.json",
        "file_extension": "xml",
        "duration": 31.7
    },
    {
        "question": "How many hours of continuous operation can the IsoMatch Tellus operate before flattening a typical tractor battery if left switched on with the engine off?",
        "expected_answer": "Not found in context",
        "model_answer": "The answer is not explicitly stated in the provided text. However, based on the context, we can infer that the IsoMatch Tellus can operate for 2 hours before a typical tractor battery needs to be flattened if left switched on with the engine off.\n\nThe text states: \"Der Schlepper muss mit einer Kat. 2 Dreipunkt-Kraftheber ausgestattet sein oder mit Zwischenbock (Zubeh\u00f6r) f\u00fcr Schlepper mit Kraftheber der Kat. 3 / 4.\" This suggests that the tractor has a type of battery with a capacity to operate for 2 hours.\n\nThe text also mentions \"Der gr\u00f6\u00dfte Arbeitswinkel der Gelenkwelle betr\u00e4gt nach oben 30 \u00b0 und 30 \u00b0 nach unten\" which implies that the maximum operating time is related to the angle of the gear, but it does not provide an explicit answer.",
        "target_page": 34,
        "context_type": "token",
        "noise_level": 30000,
        "model_name": "llama3.1_8B-128k",
        "self_evaluation": "no",
        "dataset": "question_datasets/question_answers_unanswerable.json",
        "file_extension": "xml",
        "duration": 18.6
    },
    {
        "question": "What specific 'grease' type is recommended for 'profiled tubes' of the  coupling shaft?",
        "expected_answer": "Not found in context",
        "model_answer": "The answer to this question can be found in the text on page 37.\n\nThe recommended grease type for 'profiled tubes' of the coupling shaft is EP 00/000.",
        "target_page": 51,
        "context_type": "token",
        "noise_level": 30000,
        "model_name": "llama3.1_8B-128k",
        "self_evaluation": "no",
        "dataset": "question_datasets/question_answers_unanswerable.json",
        "file_extension": "xml",
        "duration": 16.3
    },
    {
        "question": "What is the 'hose coupling support' made of?",
        "expected_answer": "Not found in context",
        "model_answer": "The \"Hose coupling\" or \"hose coupling\" mentioned in the text is not a specific component but rather a general term for a part of the machine. However, based on the context, I can infer that it refers to the flexible hose used to connect the implement to the tractor.\n\nIn the provided text, there are several mentions of the word \"Hose\", which seems to refer to different parts of the machine:\n\n1. In page 49, it says: \"Die mitgelieferte Gelenkwelle ist f\u00fcr die meisten Schleppertypen zu lang\" (The delivered drive shaft is too long for most tractor types).\n2. In page 51, it says: \"Der gr\u00f6\u00dfte Arbeitswinkel der Gelenkwelle betr\u00e4gt nach oben 30 \u00b0 und 30 \u00b0 nach unten.\" (The largest working angle of the drive shaft is 30\u00b0 and 30\u00b0 below.)\n3. In page 52, it mentions \"Hose\" in the context of a component called \"Gelenkwellenl\u00e4nge\" (Drive shaft length).\n\nBased on these references, I can conclude that the \"hose coupling support\" or \"hose coupling\" is likely referring to the flexible hose used for connecting the implement to the tractor.",
        "target_page": 55,
        "context_type": "token",
        "noise_level": 30000,
        "model_name": "llama3.1_8B-128k",
        "self_evaluation": "no",
        "dataset": "question_datasets/question_answers_unanswerable.json",
        "file_extension": "xml",
        "duration": 19.8
    },
    {
        "question": "What specific type of 'Delicia Schnecken Linsen' slug pellets were used for the spreading chart example?",
        "expected_answer": "Not found in context",
        "model_answer": "The text does not explicitly state what type of \"Delicia Schnecken Linsen\" or \"Slug Pellets\" were used for the spreading chart example. However, based on the context, we can infer that they are types of seed.\n\nSoil conditioners are seeds that are designed to be spread evenly and consistently over a given area. They are typically made from seeds with different shapes and sizes, such as Delicia Schnecken Linsen or Slug Pellets.",
        "target_page": 69,
        "context_type": "token",
        "noise_level": 30000,
        "model_name": "llama3.1_8B-128k",
        "self_evaluation": "no",
        "dataset": "question_datasets/question_answers_unanswerable.json",
        "file_extension": "xml",
        "duration": 17.2
    },
    {
        "question": "What is the minimum 'baud rate' for 'RS 232 connection'?",
        "expected_answer": "Not found in context",
        "model_answer": "The answer to this question can be found in the text on page 55.\n\nThe minimum baud rate for 'RS 232 connection' is not explicitly mentioned. However, we can infer from the context that the correct baud rate should be used according to the manufacturer's specifications or recommendations.\n\nIn the text on page 55, it says: \"Verwenden Sie den Anschlusspunkt, der in derselben Streutabelle angegeben ist.\"\n\nThis suggests that the baud rate is specified in the table.",
        "target_page": 72,
        "context_type": "token",
        "noise_level": 30000,
        "model_name": "llama3.1_8B-128k",
        "self_evaluation": "no",
        "dataset": "question_datasets/question_answers_unanswerable.json",
        "file_extension": "xml",
        "duration": 17.3
    },
    {
        "question": "What is the maximum acceptable 'chunk' size of fertilizer in mm to prevent blockage?",
        "expected_answer": "Not found in context",
        "model_answer": "The answer is: 4.75mm",
        "target_page": 74,
        "context_type": "token",
        "noise_level": 30000,
        "model_name": "llama3.1_8B-128k",
        "self_evaluation": "no",
        "dataset": "question_datasets/question_answers_unanswerable.json",
        "file_extension": "xml",
        "duration": 15.8
    },
    {
        "question": "What is the 'tap' material used for hydraulic border spreading plate tap?",
        "expected_answer": "Not found in context",
        "model_answer": "The \"Tap\" material used for hydraulic border spreading plate is not mentioned in the provided text.",
        "target_page": 85,
        "context_type": "token",
        "noise_level": 30000,
        "model_name": "llama3.1_8B-128k",
        "self_evaluation": "yes",
        "dataset": "question_datasets/question_answers_unanswerable.json",
        "file_extension": "xml",
        "duration": 16.0
    },
    {
        "question": "What type of 'active carbon filters' are recommended for closed tractor cabin to filter fertilizer dust?",
        "expected_answer": "Not found in context",
        "model_answer": "The answer is: \"Filter bags\"",
        "target_page": 94,
        "context_type": "token",
        "noise_level": 30000,
        "model_name": "llama3.1_8B-128k",
        "self_evaluation": "no",
        "dataset": "question_datasets/question_answers_unanswerable.json",
        "file_extension": "xml",
        "duration": 15.8
    },
    {
        "question": "What is the tolerance for 'measured distance from the bottom of the vanes, the distance to the ground or the crop' in cm?",
        "expected_answer": "Not found in context",
        "model_answer": "The tolerance for 'measured distance from the bottom of the vanes, the distance to the ground or the crop' is 75 cm.",
        "target_page": 95,
        "context_type": "token",
        "noise_level": 30000,
        "model_name": "llama3.1_8B-128k",
        "self_evaluation": "no",
        "dataset": "question_datasets/question_answers_unanswerable.json",
        "file_extension": "xml",
        "duration": 16.2
    },
    {
        "question": "What is the typical 'wind speed' limit in m/sec before spreading quality becomes unacceptable?",
        "expected_answer": "Not found in context",
        "model_answer": "The text does not explicitly state a specific wind speed limit. However, based on the context of the document, we can infer that the typical 'wind speed' limit is 3 m/s (Windst\u00e4rke 2).",
        "target_page": 96,
        "context_type": "token",
        "noise_level": 30000,
        "model_name": "llama3.1_8B-128k",
        "self_evaluation": "no",
        "dataset": "question_datasets/question_answers_unanswerable.json",
        "file_extension": "xml",
        "duration": 16.4
    },
    {
        "question": "What is the recommended tire pressure 'range' for transport mode?",
        "expected_answer": "Not found in context",
        "model_answer": "The recommended tire pressure range for transport mode is 2.5 to 3 bar (36-43 psi).",
        "target_page": 93,
        "context_type": "token",
        "noise_level": 30000,
        "model_name": "llama3.1_8B-128k",
        "self_evaluation": "no",
        "dataset": "question_datasets/question_answers_unanswerable.json",
        "file_extension": "xml",
        "duration": 16.0
    },
    {
        "question": "What is the optimal driving speed reduction percentage during border spreading to compensate for application rate?",
        "expected_answer": "Not found in context",
        "model_answer": "The optimal driving speed reduction percentage during border spreading to compensate for application rate is 75%.",
        "target_page": 106,
        "context_type": "token",
        "noise_level": 30000,
        "model_name": "llama3.1_8B-128k",
        "self_evaluation": "no",
        "dataset": "question_datasets/question_answers_unanswerable.json",
        "file_extension": "xml",
        "duration": 16.0
    },
    {
        "question": "What is the distance tolerance in meters from field edge when driving 'first path' for border spreading?",
        "expected_answer": "Not found in context",
        "model_answer": "The distance tolerance is 0.3 meters.",
        "target_page": 109,
        "context_type": "token",
        "noise_level": 30000,
        "model_name": "llama3.1_8B-128k",
        "self_evaluation": "no",
        "dataset": "question_datasets/question_answers_unanswerable.json",
        "file_extension": "xml",
        "duration": 15.8
    },
    {
        "question": "Can the parking support withstand storage on a slope of 10 degrees?",
        "expected_answer": "Not found in context",
        "model_answer": "The answer is: \"No\"",
        "target_page": 119,
        "context_type": "token",
        "noise_level": 30000,
        "model_name": "llama3.1_8B-128k",
        "self_evaluation": "no",
        "dataset": "question_datasets/question_answers_unanswerable.json",
        "file_extension": "xml",
        "duration": 15.8
    },
    {
        "question": "What should be done at the start of the spring season, specifically to 'prepare it for the work', beyond cleaning and lubrication?",
        "expected_answer": "Not found in context",
        "model_answer": "The text does not provide a clear answer to the question. However, based on the context, I will try to infer what is being asked.\n\nIt seems like the question is asking about the steps to be taken at the start of the spring season for the machine, specifically to prepare it for work, beyond cleaning and lubrication.\n\nThe answer should be a list of tasks that need to be done before starting the machine in the spring season.",
        "target_page": 121,
        "context_type": "token",
        "noise_level": 30000,
        "model_name": "llama3.1_8B-128k",
        "self_evaluation": "no",
        "dataset": "question_datasets/question_answers_unanswerable.json",
        "file_extension": "xml",
        "duration": 17.1
    },
    {
        "question": "How many operational hours can 'vanes' typically last before requiring replacement?",
        "expected_answer": "Not found in context",
        "model_answer": "The answer is not explicitly stated in the text. However, based on the context, we can infer that a typical maintenance cycle for the machine includes 100 hours of operation before requiring replacement.\n\nTherefore, the answer to the question \"How many operational hours can 'vanes' typically last before requiring replacement?\" is: \n\n100",
        "target_page": 125,
        "context_type": "token",
        "noise_level": 30000,
        "model_name": "llama3.1_8B-128k",
        "self_evaluation": "no",
        "dataset": "question_datasets/question_answers_unanswerable.json",
        "file_extension": "xml",
        "duration": 16.7
    },
    {
        "question": "What type of 'universal grease' is recommended for all 'lubricating nipples'?",
        "expected_answer": "Not found in context",
        "model_answer": "The answer to this question can be found in the table on page 126. The recommended type of \"universal grease\" is EP00/000 Getriebefett or Castrol GS2 or MIL-L-2105C, SAE 80W-90.",
        "target_page": 126,
        "context_type": "token",
        "noise_level": 30000,
        "model_name": "llama3.1_8B-128k",
        "self_evaluation": "no",
        "dataset": "question_datasets/question_answers_unanswerable.json",
        "file_extension": "xml",
        "duration": 16.5
    },
    {
        "question": "What type of 'suitable lubricant' is recommended for 'connectors' to prevent corrosion?",
        "expected_answer": "Not found in context",
        "model_answer": "The text does not explicitly state what type of lubricant is suitable for connectors. However, based on the context, it can be inferred that a suitable lubricant would be one that prevents corrosion.\n\nIn the section \"Wartung\" (maintenance), there are several mentions of lubricants and their uses:\n\n* In the table on page 124, it says: \"Schmier\u00f6l\" is recommended for the Gelenkwelle.\n* On page 127, it says: \"Fett anbringen oder beif\u00fcllen\" (grease or grease) is mentioned as a maintenance task.\n* On page 128, it mentions \"\u00d6l anbringen\" (oil) as part of the maintenance tasks.\n\nBased on this information, it can be inferred that a suitable lubricant for connectors would be oil or grease.",
        "target_page": 128,
        "context_type": "token",
        "noise_level": 30000,
        "model_name": "llama3.1_8B-128k",
        "self_evaluation": "no",
        "dataset": "question_datasets/question_answers_unanswerable.json",
        "file_extension": "xml",
        "duration": 18.3
    },
    {
        "question": "What 'screwdriver' type (flathead/phillips) is optimal for adjusting 'dosing mechanism'?",
        "expected_answer": "Not found in context",
        "model_answer": "The screwdriver type (flathead/Phillips) is suitable for adjusting the dosing mechanism.",
        "target_page": 133,
        "context_type": "token",
        "noise_level": 30000,
        "model_name": "llama3.1_8B-128k",
        "self_evaluation": "no",
        "dataset": "question_datasets/question_answers_unanswerable.json",
        "file_extension": "xml",
        "duration": 16.0
    },
    {
        "question": "What is the typical agitator 'seal ring' lifespan in operational hours before requiring replacement?",
        "expected_answer": "Not found in context",
        "model_answer": "The lifespan of a seal ring for the Gelenkwelle (Zentralgetriebe) is typically 10,000 to 15,000 hours.",
        "target_page": 134,
        "context_type": "token",
        "noise_level": 30000,
        "model_name": "llama3.1_8B-128k",
        "self_evaluation": "no",
        "dataset": "question_datasets/question_answers_unanswerable.json",
        "file_extension": "xml",
        "duration": 16.1
    },
    {
        "question": "What is the 'small crack of light' dimension in millimeters between 'dosing baffles' when closed?",
        "expected_answer": "Not found in context",
        "model_answer": "The \"small crack of light\" is 1.0 mm.",
        "target_page": 135,
        "context_type": "token",
        "noise_level": 30000,
        "model_name": "llama3.1_8B-128k",
        "self_evaluation": "no",
        "dataset": "question_datasets/question_answers_unanswerable.json",
        "file_extension": "xml",
        "duration": 15.9
    },
    {
        "question": "What type of 'feeler gauge' material is recommended for 'discharge bushing height' check?",
        "expected_answer": "Not found in context",
        "model_answer": "The answer to this question can be found in the text on page 138. The recommended material for 'feeler gauge' is not explicitly mentioned, but the text mentions \"Mittelschrauben\" which are used to check the height of the discharge bushing.",
        "target_page": 138,
        "context_type": "token",
        "noise_level": 30000,
        "model_name": "llama3.1_8B-128k",
        "self_evaluation": "no",
        "dataset": "question_datasets/question_answers_unanswerable.json",
        "file_extension": "xml",
        "duration": 16.5
    },
    {
        "question": "What is the 'plastic seal' material specification for agitator axle seal?",
        "expected_answer": "Not found in context",
        "model_answer": "The answer to the question \"What is the 'plastic seal' material specification for agitator axle seal?\" is not explicitly stated in the provided text. However, based on the context, I can infer that the plastic seal mentioned is likely a type of O-rings or seals used in the hydraulic system.\n\nIn the section about \"Dichtung Agitatorwelle austauschen\" (page 140), it says: \"Die Dichtungen sind mit Kunststoff gef\u00fcllt.\" which translates to \"The seals are filled with plastic.\"\n\nTherefore, I will provide a general answer based on this information:\n\nThe 'plastic seal' material specification for agitator axle seal is likely O-rings or similar types of hydraulic seals made from plastic.",
        "target_page": 140,
        "context_type": "token",
        "noise_level": 30000,
        "model_name": "llama3.1_8B-128k",
        "self_evaluation": "no",
        "dataset": "question_datasets/question_answers_unanswerable.json",
        "file_extension": "xml",
        "duration": 18.1
    },
    {
        "question": "What is the material of the 'metal seal rings' for agitator axle seal?",
        "expected_answer": "Not found in context",
        "model_answer": "The material of the \"metallische Dichtungsringe\" (metallic seal rings) for agitator axle seal is not specified in the provided text.",
        "target_page": 141,
        "context_type": "token",
        "noise_level": 30000,
        "model_name": "llama3.1_8B-128k",
        "self_evaluation": "yes",
        "dataset": "question_datasets/question_answers_unanswerable.json",
        "file_extension": "xml",
        "duration": 16.2
    },
    {
        "question": "What specific 'extension cable' length in meters is optimal for ISO 11786 in cab tractor connection?",
        "expected_answer": "Not found in context",
        "model_answer": "The answer to this question can be found on page 142 of the manual. The text states: \"Ein verl\u00e4ngertes ISO-Kabel ist verf\u00fcgbar.\" which translates to \"A lengthened ISO-cable is available.\"\n\nThis means that a longer ISO cable, specifically an extension cable for the ISO 11786 'In Cab' connection, is available for use in the cab tractor.",
        "target_page": 144,
        "context_type": "token",
        "noise_level": 30000,
        "model_name": "llama3.1_8B-128k",
        "self_evaluation": "no",
        "dataset": "question_datasets/question_answers_unanswerable.json",
        "file_extension": "xml",
        "duration": 16.9
    },
    {
        "question": "What is the free 'test period' duration in days for 'GEOCONTROL software' user licence?",
        "expected_answer": "Not found in context",
        "model_answer": "The answer to this question can be found on page 145 of the manual. The free 'test period' duration for 'GEOCONTROL software' user license is not explicitly stated in the provided text. However, based on the context, we can infer that it is 30 days.\n\nOn page 145, it says: \"\u00dcber den IsoMatch Shop k\u00f6nnen Sie eine Nutzungslizenz erwerben, die ihre Maschine nach Ablauf des Gratistestzeitraums arbeiten l\u00e4sst mit\" which translates to \"You can obtain a user license for your machine after the end of the warranty period\". This implies that the warranty period is 30 days.\n\nTherefore, we can conclude that the free 'test period' duration for 'GEOCONTROL software' user license is 30 days.",
        "target_page": 145,
        "context_type": "token",
        "noise_level": 30000,
        "model_name": "llama3.1_8B-128k",
        "self_evaluation": "no",
        "dataset": "question_datasets/question_answers_unanswerable.json",
        "file_extension": "xml",
        "duration": 2.8
    },
    {
        "question": "What valve type and manufacturer is used for 'valve set' that comes with hopper empty sensor?",
        "expected_answer": "Not found in context",
        "model_answer": "The valve type and manufacturer used for \"valve set\" is ExactLine.",
        "target_page": 148,
        "context_type": "token",
        "noise_level": 30000,
        "model_name": "llama3.1_8B-128k",
        "self_evaluation": "no",
        "dataset": "question_datasets/question_answers_unanswerable.json",
        "file_extension": "xml",
        "duration": 0.5
    },
    {
        "question": "What is the drain rate in liters per minute of 'drain kit' for hopper emptying?",
        "expected_answer": "Not found in context",
        "model_answer": "The answer to this question cannot be found in the provided text.",
        "target_page": 149,
        "context_type": "token",
        "noise_level": 30000,
        "model_name": "llama3.1_8B-128k",
        "self_evaluation": "yes",
        "dataset": "question_datasets/question_answers_unanswerable.json",
        "file_extension": "xml",
        "duration": 0.5
    },
    {
        "question": "What 'sail' material is used for hopper cover, and its UV resistance?",
        "expected_answer": "Not found in context",
        "model_answer": "The answer to the question \"What'sail material is used for hopper cover, and its UV resistance?\" is not explicitly stated in the provided text. However, based on general knowledge about hopper covers, I can provide an educated guess.\n\nHopper covers are typically made from a durable material that provides protection against wear and tear, as well as exposure to the elements (sunlight, rain, etc.). A common material used for hopper covers is HDPE (High-Density Polyethylene), which has good UV resistance.",
        "target_page": 150,
        "context_type": "token",
        "noise_level": 30000,
        "model_name": "llama3.1_8B-128k",
        "self_evaluation": "no",
        "dataset": "question_datasets/question_answers_unanswerable.json",
        "file_extension": "xml",
        "duration": 1.9
    }
]